Workbook
Name UPDATE: 'Data Sheet'!$E$1

Sheet FINANCIALS>

Sheet HISTORIACLFINANCIALS
B2: ="HISTORICAL FINANCIAL STATEMENT - "&'Data Sheet'!B1 -> HISTORICAL FINANCIAL STATEMENT - MARUTI SUZUKI INDIA LTD
B3: YEARS | C3: ='Data Sheet'!B16 -> 42460 | D3: ='Data Sheet'!C16 -> 42825 | E3: ='Data Sheet'!D16 -> 43190 | F3: ='Data Sheet'!E16 -> 43555 | G3: ='Data Sheet'!F16 -> 43921 | H3: ='Data Sheet'!G16 -> 44286 | I3: ='Data Sheet'!H16 -> 44651 | J3: ='Data Sheet'!I16 -> 45016 | ... L3: ='Data Sheet'!K16 -> 45747 | M3: LTM
A4: # | B4: INCOME STATEMENT (in cr.)
B5: SALES | C5: =IFERROR('Data Sheet'!B17,0) -> 57589 | D5: =IFERROR('Data Sheet'!C17,0) -> 68085 | E5: =IFERROR('Data Sheet'!D17,0) -> 79809.4 | F5: =IFERROR('Data Sheet'!E17,0) -> 86068.5 | G5: =IFERROR('Data Sheet'!F17,0) -> 75660 | H5: =IFERROR('Data Sheet'!G17,0) -> 70372 | I5: =IFERROR('Data Sheet'!H17,0) -> 88329.8 | J5: =IFERROR('Data Sheet'!I17,0) -> 117571.3 | ... L5: =IFERROR('Data Sheet'!K17,0) -> 152913 | M5: =IFERROR(SUM('Data Sheet'!H42:K42),0) -> 171773.6
B6: SALES GROWTH | C6: - | D6: =D5/C5-1 -> 0.18225703 | E6: =E5/D5-1 -> 0.17220239 | F6: =F5/E5-1 -> 0.078425599 | G6: =G5/F5-1 -> -0.12093275 | H6: =H5/G5-1 -> -0.06989162 | I6: =I5/H5-1 -> 0.25518388 | J6: =J5/I5-1 -> 0.33104909 | K6: =K5/J5-1 -> 0.20657167 | ... M6: =M5/L5-1 -> 0.12334203
B8: COGS | C8: =IFERROR(SUM('Data Sheet'!B18,'Data Sheet'!B20:B22)-1*'Data Sheet'!B19,0) -> 41828.2 | D8: =IFERROR(SUM('Data Sheet'!C18,'Data Sheet'!C20:C22)-1*'Data Sheet'!C19,0) -> 50004 | E8: =IFERROR(SUM('Data Sheet'!D18,'Data Sheet'!D20:D22)-1*'Data Sheet'!D19,0) -> 58985 | F8: =IFERROR(SUM('Data Sheet'!E18,'Data Sheet'!E20:E22)-1*'Data Sheet'!E19,0) -> 64182.2 | G8: =IFERROR(SUM('Data Sheet'!F18,'Data Sheet'!F20:F22)-1*'Data Sheet'!F19,0) -> 57657.1 | H8: =IFERROR(SUM('Data Sheet'!G18,'Data Sheet'!G20:G22)-1*'Data Sheet'!G19,0) -> 55415.6 | I8: =IFERROR(SUM('Data Sheet'!H18,'Data Sheet'!H20:H22)-1*'Data Sheet'!H19,0) -> 71578.8 | J8: =IFERROR(SUM('Data Sheet'!I18,'Data Sheet'!I20:I22)-1*'Data Sheet'!I19,0) -> 92796.1 | ... L8: =IFERROR(SUM('Data Sheet'!K18,'Data Sheet'!K20:K22)-1*'Data Sheet'!K19,0) -> 117563.8 | M8: =IFERROR(SUM('Data Sheet'!H43:K43),0) -> 151647.9
B9: COGS%SALES | C9: =C8/C5 -> 0.72632274 | D9: =D8/D5 -> 0.7344349 | E9: =E8/E5 -> 0.73907334 | F9: =F8/F5 -> 0.74571068 | G9: =G8/G5 -> 0.76205525 | H9: =H8/H5 -> 0.78746661 | I9: =I8/I5 -> 0.81035845 | J9: =J8/J5 -> 0.7892751 | ... M9: =M8/M5 -> 0.8828359
B11: GROSS PROFIT | C11: =IFERROR(C5-C8,0) -> 15760.8 | D11: =IFERROR(D5-D8,0) -> 18081 | E11: =IFERROR(E5-E8,0) -> 20824.4 | F11: =IFERROR(F5-F8,0) -> 21886.3 | G11: =IFERROR(G5-G8,0) -> 18002.9 | H11: =IFERROR(H5-H8,0) -> 14956.4 | I11: =IFERROR(I5-I8,0) -> 16751 | J11: =IFERROR(J5-J8,0) -> 24775.2 | ... M11: =IFERROR(M5-M8,0) -> 20125.7
B12: GROSS MARGIN | C12: =IFERROR(C11/C5,0) -> 0.27367726 | D12: =IFERROR(D11/D5,0) -> 0.2655651 | E12: =IFERROR(E11/E5,0) -> 0.26092666 | F12: =IFERROR(F11/F5,0) -> 0.25428932 | G12: =IFERROR(G11/G5,0) -> 0.23794475 | H12: =IFERROR(H11/H5,0) -> 0.21253339 | I12: =IFERROR(I11/I5,0) -> 0.18964155 | J12: =IFERROR(J11/J5,0) -> 0.2107249 | ... M12: =IFERROR(M11/M5,0) -> 0.1171641
B14: S&G EXPENSES | C14: =IFERROR(SUM('Data Sheet'!B23,'Data Sheet'!B24),0) -> 6736.7 | D14: =IFERROR(SUM('Data Sheet'!C23,'Data Sheet'!C24),0) -> 7659.7 | E14: =IFERROR(SUM('Data Sheet'!D23,'Data Sheet'!D24),0) -> 8706.5 | F14: =IFERROR(SUM('Data Sheet'!E23,'Data Sheet'!E24),0) -> 10830 | G14: =IFERROR(SUM('Data Sheet'!F23,'Data Sheet'!F24),0) -> 10647.9 | H14: =IFERROR(SUM('Data Sheet'!G23,'Data Sheet'!G24),0) -> 9545.8 | I14: =IFERROR(SUM('Data Sheet'!H23,'Data Sheet'!H24),0) -> 10999 | J14: =IFERROR(SUM('Data Sheet'!I23,'Data Sheet'!I24),0) -> 13746 | ... L14: =IFERROR(SUM('Data Sheet'!K23,'Data Sheet'!K24),0) -> 15125.6
B15: S&G EXPENSES%SALES | C15: =IFERROR(C14/C5,0) -> 0.11697894 | D15: =IFERROR(D14/D5,0) -> 0.11250202 | E15: =IFERROR(E14/E5,0) -> 0.10909116 | F15: =IFERROR(F14/F5,0) -> 0.12583001 | G15: =IFERROR(G14/G5,0) -> 0.14073354 | H15: =IFERROR(H14/H5,0) -> 0.1356477 | I15: =IFERROR(I14/I5,0) -> 0.12452196 | J15: =IFERROR(J14/J5,0) -> 0.11691629 | ... M15: =IFERROR(M14/M5,0) -> 0
B17: EBITDA | C17: =IFERROR(C5-C8-C14,0) -> 9024.1 | D17: =IFERROR(D5-D8-D14,0) -> 10421.3 | E17: =IFERROR(E5-E8-E14,0) -> 12117.9 | F17: =IFERROR(F5-F8-F14,0) -> 11056.3 | G17: =IFERROR(G5-G8-G14,0) -> 7355 | H17: =IFERROR(H5-H8-H14,0) -> 5410.6 | I17: =IFERROR(I5-I8-I14,0) -> 5752 | J17: =IFERROR(J5-J8-J14,0) -> 11029.2 | ... M17: =IFERROR(M5-M8-M14,0) -> 20125.7
B18: EBITDA%SALES | C18: =IFERROR(C17/C5,0) -> 0.15669833 | D18: =IFERROR(D17/D5,0) -> 0.15306308 | E18: =IFERROR(E17/E5,0) -> 0.1518355 | F18: =IFERROR(F17/F5,0) -> 0.12845931 | G18: =IFERROR(G17/G5,0) -> 0.097211208 | H18: =IFERROR(H17/H5,0) -> 0.076885693 | I18: =IFERROR(I17/I5,0) -> 0.065119586 | J18: =IFERROR(J17/J5,0) -> 0.093808608 | ... M18: =IFERROR(M17/M5,0) -> 0.1171641
B20: INTEREST | C20: =IFERROR('Data Sheet'!B27,0) -> 81.7 | D20: =IFERROR('Data Sheet'!C27,0) -> 89.4 | E20: =IFERROR('Data Sheet'!D27,0) -> 345.8 | F20: =IFERROR('Data Sheet'!E27,0) -> 75.9 | G20: =IFERROR('Data Sheet'!F27,0) -> 134.2 | H20: =IFERROR('Data Sheet'!G27,0) -> 101.8 | I20: =IFERROR('Data Sheet'!H27,0) -> 126.6 | J20: =IFERROR('Data Sheet'!I27,0) -> 187 | ... L20: =IFERROR('Data Sheet'!K27,0) -> 194.2 | M20: =IFERROR(SUM('Data Sheet'!H46:K46),0) -> 213.3
B21: INTEREST%SALES | C21: =IFERROR(C20/C5,0) -> 0.0014186737 | D21: =IFERROR(D20/D5,0) -> 0.0013130646 | E21: =IFERROR(E20/E5,0) -> 0.004332823 | F21: =IFERROR(F20/F5,0) -> 0.00088185573 | G21: =IFERROR(G20/G5,0) -> 0.0017737246 | H21: =IFERROR(H20/H5,0) -> 0.0014465981 | I21: =IFERROR(I20/I5,0) -> 0.0014332649 | J21: =IFERROR(J20/J5,0) -> 0.0015905242 | ... M21: =IFERROR(M20/M5,0) -> 0.0012417508
B23: DEPRECIATION | C23: =IFERROR('Data Sheet'!C26,0) -> 2603.9 | D23: =IFERROR('Data Sheet'!D26,0) -> 2759.8 | E23: =IFERROR('Data Sheet'!E26,0) -> 3020.8 | F23: =IFERROR('Data Sheet'!F26,0) -> 3528.4 | G23: =IFERROR('Data Sheet'!G26,0) -> 3034.1 | H23: =IFERROR('Data Sheet'!H26,0) -> 2789 | I23: =IFERROR('Data Sheet'!I26,0) -> 2825.7 | J23: =IFERROR('Data Sheet'!J26,0) -> 5255.8 | ... L23: =IFERROR('Data Sheet'!L26,0) -> 0 | M23: =IFERROR(SUM('Data Sheet'!H45:K45),0) -> 6455.4
B24: DEPRECIATION%SALES | C24: =IFERROR(C23/C5,0) -> 0.045215232 | D24: =IFERROR(D23/D5,0) -> 0.040534626 | E24: =IFERROR(E23/E5,0) -> 0.037850178 | F24: =IFERROR(F23/F5,0) -> 0.040995254 | G24: =IFERROR(G23/G5,0) -> 0.040101771 | H24: =IFERROR(H23/H5,0) -> 0.03963224 | I24: =IFERROR(I23/I5,0) -> 0.031990336 | J24: =IFERROR(J23/J5,0) -> 0.044703087 | ... M24: =IFERROR(M23/M5,0) -> 0.037580862
B26: EARNING BEFORE TAX | C26: =IFERROR(C17-C23,0) -> 6420.2 | D26: =IFERROR(D17-D23,0) -> 7661.5 | E26: =IFERROR(E17-E23,0) -> 9097.1 | F26: =IFERROR(F17-F23,0) -> 7527.9 | G26: =IFERROR(G17-G23,0) -> 4320.9 | H26: =IFERROR(H17-H23,0) -> 2621.6 | I26: =IFERROR(I17-I23,0) -> 2926.3 | J26: =IFERROR(J17-J23,0) -> 5773.4 | ... M26: =IFERROR(M17-M23,0) -> 13670.3
B27: EBT%SALES | C27: =IFERROR(C26/C5,0) -> 0.1114831 | D27: =IFERROR(D26/D5,0) -> 0.11252846 | E27: =IFERROR(E26/E5,0) -> 0.11398532 | F27: =IFERROR(F26/F5,0) -> 0.087464055 | G27: =IFERROR(G26/G5,0) -> 0.057109437 | H27: =IFERROR(H26/H5,0) -> 0.037253453 | I27: =IFERROR(I26/I5,0) -> 0.03312925 | J27: =IFERROR(J26/J5,0) -> 0.049105522 | ... M27: =IFERROR(M26/M5,0) -> 0.079583242
B29: TAX | C29: =IFERROR('Data Sheet'!B29,0) -> 2087.5 | D29: =IFERROR('Data Sheet'!C29,0) -> 2616.2 | E29: =IFERROR('Data Sheet'!D29,0) -> 3286.2 | F29: =IFERROR('Data Sheet'!E29,0) -> 2973.2 | G29: =IFERROR('Data Sheet'!F29,0) -> 1425.2 | H29: =IFERROR('Data Sheet'!G29,0) -> 931.9 | I29: =IFERROR('Data Sheet'!H29,0) -> 817.7 | J29: =IFERROR('Data Sheet'!I29,0) -> 2112.1 | ... L29: =IFERROR('Data Sheet'!K29,0) -> 5119.8 | M29: =IFERROR(SUM('Data Sheet'!H48:K48),0) -> 4186.2
B30: EFFECTIVE TAX RATE | C30: =IFERROR(C29/C26,0) -> 0.32514563 | D30: =IFERROR(D29/D26,0) -> 0.3414736 | E30: =IFERROR(E29/E26,0) -> 0.361236 | F30: =IFERROR(F29/F26,0) -> 0.39495743 | G30: =IFERROR(G29/G26,0) -> 0.32983869 | H30: =IFERROR(H29/H26,0) -> 0.35546994 | I30: =IFERROR(I29/I26,0) -> 0.27943136 | J30: =IFERROR(J29/J26,0) -> 0.36583296 | ... M30: =IFERROR(M29/M26,0) -> 0.30622591
B32: NET PROFIT | C32: =IFERROR(C26-C29,0) -> 4332.7 | D32: =IFERROR(D26-D29,0) -> 5045.3 | E32: =IFERROR(E26-E29,0) -> 5810.9 | F32: =IFERROR(F26-F29,0) -> 4554.7 | G32: =IFERROR(G26-G29,0) -> 2895.7 | H32: =IFERROR(H26-H29,0) -> 1689.7 | I32: =IFERROR(I26-I29,0) -> 2108.6 | J32: =IFERROR(J26-J29,0) -> 3661.3 | ... L32: =IFERROR(L26-L29,0) -> 15103.8 | M32: =IFERROR(SUM('Data Sheet'!H49:K49),0) -> 14931.6
B33: NET MARGINS | C33: =IFERROR(C32/C5,0) -> 0.075234854 | D33: =IFERROR(D32/D5,0) -> 0.07410296 | E33: =IFERROR(E32/E5,0) -> 0.072809719 | F33: =IFERROR(F32/F5,0) -> 0.052919477 | G33: =IFERROR(G32/G5,0) -> 0.038272535 | H33: =IFERROR(H32/H5,0) -> 0.02401097 | I33: =IFERROR(I32/I5,0) -> 0.023871898 | J33: =IFERROR(J32/J5,0) -> 0.031141103 | ... M33: =IFERROR(M32/M5,0) -> 0.086926047
B35: NO OF EQUITY SHARE | C35: =IFERROR('Data Sheet'!B93,0) -> 30.21 | D35: =IFERROR('Data Sheet'!C93,0) -> 30.21 | E35: =IFERROR('Data Sheet'!D93,0) -> 30.21 | F35: =IFERROR('Data Sheet'!E93,0) -> 30.21 | G35: =IFERROR('Data Sheet'!F93,0) -> 30.21 | H35: =IFERROR('Data Sheet'!G93,0) -> 30.21 | I35: =IFERROR('Data Sheet'!H93,0) -> 30.21 | J35: =IFERROR('Data Sheet'!I93,0) -> 30.21 | ... L35: =IFERROR('Data Sheet'!K93,0) -> 31.44 | M35: 31.44
B37: EPS | C37: =IFERROR(C32/C35,0) -> 143.4194 | D37: =IFERROR(D32/D35,0) -> 167.00761 | E37: =IFERROR(E32/E35,0) -> 192.35022 | F37: =IFERROR(F32/F35,0) -> 150.76796 | G37: =IFERROR(G32/G35,0) -> 95.852367 | H37: =IFERROR(H32/H35,0) -> 55.931811 | I37: =IFERROR(I32/I35,0) -> 69.79808 | J37: =IFERROR(J32/J35,0) -> 121.19497 | ... M37: =IFERROR(M32/M35,0) -> 474.92366
B38: EPS GROWTH% | C38: - | D38: =IFERROR(D37/C37-1,0) -> 0.16447019 | E38: =IFERROR(E37/D37-1,0) -> 0.15174519 | F38: =IFERROR(F37/E37-1,0) -> -0.21617994 | G38: =IFERROR(G37/F37-1,0) -> -0.36423914 | H38: =IFERROR(H37/G37-1,0) -> -0.41647961 | I38: =IFERROR(I37/H37-1,0) -> 0.24791383 | J38: =IFERROR(J37/I37-1,0) -> 0.73636536 | K38: =IFERROR(K37/J37-1,0) -> 1.3834432 | ... M38: =IFERROR(M37/L37-1,0) -> -0.011401104
B40: DIVIDEND PER SHARE | C40: =IFERROR('Data Sheet'!B31/HISTORIACLFINANCIALS!C35,0) -> 34.988414 | D40: =IFERROR('Data Sheet'!C31/HISTORIACLFINANCIALS!D35,0) -> 74.975174 | E40: =IFERROR('Data Sheet'!D31/HISTORIACLFINANCIALS!E35,0) -> 79.973519 | F40: =IFERROR('Data Sheet'!E31/HISTORIACLFINANCIALS!F35,0) -> 79.973519 | G40: =IFERROR('Data Sheet'!F31/HISTORIACLFINANCIALS!G35,0) -> 59.980139 | H40: =IFERROR('Data Sheet'!G31/HISTORIACLFINANCIALS!H35,0) -> 44.985104 | I40: =IFERROR('Data Sheet'!H31/HISTORIACLFINANCIALS!I35,0) -> 59.980139 | J40: =IFERROR('Data Sheet'!I31/HISTORIACLFINANCIALS!J35,0) -> 89.970209 | ... M40: =IFERROR('Data Sheet'!L31/HISTORIACLFINANCIALS!M35,0) -> 0
B41: DIVIDEND PAY OUT RATIO | C41: =IFERROR(C40/C37,0) -> 0.24395873 | D41: =IFERROR(D40/D37,0) -> 0.44893267 | E41: =IFERROR(E40/E37,0) -> 0.41577036 | F41: =IFERROR(F40/F37,0) -> 0.53044108 | G41: =IFERROR(G40/G37,0) -> 0.62575543 | H41: =IFERROR(H40/H37,0) -> 0.80428478 | I41: =IFERROR(I40/I37,0) -> 0.85933795 | J41: =IFERROR(J40/J37,0) -> 0.74235927 | ... M41: =IFERROR(M40/M37,0) -> 0
B43: RETAINED EARNING | C43: =IFERROR(1-C41,0) -> 0.75604127 | D43: =IFERROR(1-D41,0) -> 0.55106733 | E43: =IFERROR(1-E41,0) -> 0.58422964 | F43: =IFERROR(1-F41,0) -> 0.46955892 | G43: =IFERROR(1-G41,0) -> 0.37424457 | H43: =IFERROR(1-H41,0) -> 0.19571522 | I43: =IFERROR(1-I41,0) -> 0.14066205 | J43: =IFERROR(1-J41,0) -> 0.25764073 | ... M43: =IFERROR(1-M41,0) -> 1
A45: # | B45: BALANCE SHEET (in cr.)
B46: =IFERROR('Data Sheet'!A57,0) -> Equity Share Capital | C46: =IFERROR('Data Sheet'!B57,0) -> 151 | D46: =IFERROR('Data Sheet'!C57,0) -> 151 | E46: =IFERROR('Data Sheet'!D57,0) -> 151 | F46: =IFERROR('Data Sheet'!E57,0) -> 151 | G46: =IFERROR('Data Sheet'!F57,0) -> 151 | H46: =IFERROR('Data Sheet'!G57,0) -> 151 | I46: =IFERROR('Data Sheet'!H57,0) -> 151 | ... L46: =IFERROR('Data Sheet'!K57,0) -> 157.2
B47: =IFERROR('Data Sheet'!A58,0) -> Reserves | C47: =IFERROR('Data Sheet'!B58,0) -> 30465 | D47: =IFERROR('Data Sheet'!C58,0) -> 36924.1 | E47: =IFERROR('Data Sheet'!D58,0) -> 42408.4 | F47: =IFERROR('Data Sheet'!E58,0) -> 46941.1 | G47: =IFERROR('Data Sheet'!F58,0) -> 49262 | H47: =IFERROR('Data Sheet'!G58,0) -> 52349.6 | I47: =IFERROR('Data Sheet'!H58,0) -> 55182.5 | ... L47: =IFERROR('Data Sheet'!K58,0) -> 96082.7
B48: =IFERROR('Data Sheet'!A59,0) -> Borrowings | C48: =IFERROR('Data Sheet'!B59,0) -> 230.9 | D48: =IFERROR('Data Sheet'!C59,0) -> 483.6 | E48: =IFERROR('Data Sheet'!D59,0) -> 120.8 | F48: =IFERROR('Data Sheet'!E59,0) -> 159.6 | G48: =IFERROR('Data Sheet'!F59,0) -> 184.1 | H48: =IFERROR('Data Sheet'!G59,0) -> 540.9 | I48: =IFERROR('Data Sheet'!H59,0) -> 425.5 | ... L48: =IFERROR('Data Sheet'!K59,0) -> 87
B49: =IFERROR('Data Sheet'!A60,0) -> Other Liabilities | C49: =IFERROR('Data Sheet'!B60,0) -> 11878.6 | D49: =IFERROR('Data Sheet'!C60,0) -> 14401.8 | E49: =IFERROR('Data Sheet'!D60,0) -> 17568.2 | F49: =IFERROR('Data Sheet'!E60,0) -> 16717 | G49: =IFERROR('Data Sheet'!F60,0) -> 14030.6 | H49: =IFERROR('Data Sheet'!G60,0) -> 18334.6 | I49: =IFERROR('Data Sheet'!H60,0) -> 18896.5 | ... L49: =IFERROR('Data Sheet'!K60,0) -> 35644.3
B50: TOTAL LIABILITIES | C50: =IFERROR(SUM(C46:C49),0) -> 42725.5 | D50: =IFERROR(SUM(D46:D49),0) -> 51960.5 | E50: =IFERROR(SUM(E46:E49),0) -> 60248.4 | F50: =IFERROR(SUM(F46:F49),0) -> 63968.7 | G50: =IFERROR(SUM(G46:G49),0) -> 63627.7 | H50: =IFERROR(SUM(H46:H49),0) -> 71376.1 | I50: =IFERROR(SUM(I46:I49),0) -> 74655.5 | J50: =IFERROR(SUM(J46:J49),0) -> 84596.9 | ... L50: =IFERROR(SUM(L46:L49),0) -> 131971.2
B52: Fixed Asset Net Block | C52: =IFERROR('Data Sheet'!B62,0) -> 12529.6 | D52: =IFERROR('Data Sheet'!C62,0) -> 13310.7 | E52: =IFERROR('Data Sheet'!D62,0) -> 13388.8 | F52: =IFERROR('Data Sheet'!E62,0) -> 15437.3 | G52: =IFERROR('Data Sheet'!F62,0) -> 15744.4 | H52: =IFERROR('Data Sheet'!G62,0) -> 14988.7 | I52: =IFERROR('Data Sheet'!H62,0) -> 13747.2 | J52: =IFERROR('Data Sheet'!I62,0) -> 17830.4 | ... L52: =IFERROR('Data Sheet'!K62,0) -> 32982.7
B53: =IFERROR('Data Sheet'!A63,0) -> Capital Work in Progress | C53: =IFERROR('Data Sheet'!B63,0) -> 1006.9 | D53: =IFERROR('Data Sheet'!C63,0) -> 1252.3 | E53: =IFERROR('Data Sheet'!D63,0) -> 2132.1 | F53: =IFERROR('Data Sheet'!E63,0) -> 1606.9 | G53: =IFERROR('Data Sheet'!F63,0) -> 1415.2 | H53: =IFERROR('Data Sheet'!G63,0) -> 1496.8 | I53: =IFERROR('Data Sheet'!H63,0) -> 2936.5 | ... L53: =IFERROR('Data Sheet'!K63,0) -> 7929
B54: =IFERROR('Data Sheet'!A64,0) -> Investments | C54: =IFERROR('Data Sheet'!B64,0) -> 20675.8 | D54: =IFERROR('Data Sheet'!C64,0) -> 29150.6 | E54: =IFERROR('Data Sheet'!D64,0) -> 36123.1 | F54: =IFERROR('Data Sheet'!E64,0) -> 37503.6 | G54: =IFERROR('Data Sheet'!F64,0) -> 37488 | H54: =IFERROR('Data Sheet'!G64,0) -> 42944.8 | I54: =IFERROR('Data Sheet'!H64,0) -> 42034.7 | ... L54: =IFERROR('Data Sheet'!K64,0) -> 66265.4
B55: =IFERROR('Data Sheet'!A65,0) -> Other Assets | C55: =IFERROR('Data Sheet'!B65-SUM('Data Sheet'!B67:B69),0) -> 4006.5 | D55: =IFERROR('Data Sheet'!C65-SUM('Data Sheet'!C67:C69),0) -> 3757.1 | E55: =IFERROR('Data Sheet'!D65-SUM('Data Sheet'!D67:D69),0) -> 3904.8 | F55: =IFERROR('Data Sheet'!E65-SUM('Data Sheet'!E67:E69),0) -> 3597.7 | G55: =IFERROR('Data Sheet'!F65-SUM('Data Sheet'!F67:F69),0) -> 3759.5 | H55: =IFERROR('Data Sheet'!G65-SUM('Data Sheet'!G67:G69),0) -> 4569.8 | I55: =IFERROR('Data Sheet'!H65-SUM('Data Sheet'!H67:H69),0) -> 7328.1 | J55: =IFERROR('Data Sheet'!I65-SUM('Data Sheet'!I67:I69),0) -> 7051.6 | ... L55: =IFERROR('Data Sheet'!K65-SUM('Data Sheet'!K67:K69),0) -> 10788.3
B56: Total Non-Current Assets | C56: =IFERROR(SUM(C52:C55),0) -> 38218.8 | D56: =IFERROR(SUM(D52:D55),0) -> 47470.7 | E56: =IFERROR(SUM(E52:E55),0) -> 55548.8 | F56: =IFERROR(SUM(F52:F55),0) -> 58145.5 | G56: =IFERROR(SUM(G52:G55),0) -> 58407.1 | H56: =IFERROR(SUM(H52:H55),0) -> 64000.1 | I56: =IFERROR(SUM(I52:I55),0) -> 66046.5 | J56: =IFERROR(SUM(J52:J55),0) -> 76970.4 | ... L56: =IFERROR(SUM(L52:L55),0) -> 117965.4
B58: =IFERROR('Data Sheet'!A67,0) -> Receivables | C58: =IFERROR('Data Sheet'!B67,0) -> 1323.4 | D58: =IFERROR('Data Sheet'!C67,0) -> 1202.6 | E58: =IFERROR('Data Sheet'!D67,0) -> 1465.4 | F58: =IFERROR('Data Sheet'!E67,0) -> 2312.8 | G58: =IFERROR('Data Sheet'!F67,0) -> 1977.7 | H58: =IFERROR('Data Sheet'!G67,0) -> 1279.9 | I58: =IFERROR('Data Sheet'!H67,0) -> 2034.5 | ... L58: =IFERROR('Data Sheet'!K67,0) -> 6539.7
B59: =IFERROR('Data Sheet'!A68,0) -> Inventory | C59: =IFERROR('Data Sheet'!B68,0) -> 3132.6 | D59: =IFERROR('Data Sheet'!C68,0) -> 3263.7 | E59: =IFERROR('Data Sheet'!D68,0) -> 3160.2 | F59: =IFERROR('Data Sheet'!E68,0) -> 3322.6 | G59: =IFERROR('Data Sheet'!F68,0) -> 3213.9 | H59: =IFERROR('Data Sheet'!G68,0) -> 3049 | I59: =IFERROR('Data Sheet'!H68,0) -> 3532.3 | ... L59: =IFERROR('Data Sheet'!K68,0) -> 6913.2
B60: =IFERROR('Data Sheet'!A69,0) -> Cash & Bank | C60: =IFERROR('Data Sheet'!B69,0) -> 50.7 | D60: =IFERROR('Data Sheet'!C69,0) -> 23.5 | E60: =IFERROR('Data Sheet'!D69,0) -> 74 | F60: =IFERROR('Data Sheet'!E69,0) -> 187.8 | G60: =IFERROR('Data Sheet'!F69,0) -> 29 | H60: =IFERROR('Data Sheet'!G69,0) -> 3047.1 | I60: =IFERROR('Data Sheet'!H69,0) -> 3042.2 | ... L60: =IFERROR('Data Sheet'!K69,0) -> 552.9
B61: Total Current Assests | C61: =IFERROR(SUM(C58:C60),0) -> 4506.7 | D61: =IFERROR(SUM(D58:D60),0) -> 4489.8 | E61: =IFERROR(SUM(E58:E60),0) -> 4699.6 | F61: =IFERROR(SUM(F58:F60),0) -> 5823.2 | G61: =IFERROR(SUM(G58:G60),0) -> 5220.6 | H61: =IFERROR(SUM(H58:H60),0) -> 7376 | I61: =IFERROR(SUM(I58:I60),0) -> 8609 | J61: =IFERROR(SUM(J58:J60),0) -> 7626.5 | ... L61: =IFERROR(SUM(L58:L60),0) -> 14005.8
B63: Total Assets | C63: =IFERROR(C56+C61,0) -> 42725.5 | D63: =IFERROR(D56+D61,0) -> 51960.5 | E63: =IFERROR(E56+E61,0) -> 60248.4 | F63: =IFERROR(F56+F61,0) -> 63968.7 | G63: =IFERROR(G56+G61,0) -> 63627.7 | H63: =IFERROR(H56+H61,0) -> 71376.1 | I63: =IFERROR(I56+I61,0) -> 74655.5 | J63: =IFERROR(J56+J61,0) -> 84596.9 | ... L63: =IFERROR(L56+L61,0) -> 131971.2
B65: CHECK | C65: =C50=C63 -> TRUE | D65: =D50=D63 -> TRUE | E65: =E50=E63 -> TRUE | F65: =F50=F63 -> TRUE | G65: =G50=G63 -> TRUE | H65: =H50=H63 -> TRUE | I65: =I50=I63 -> TRUE | J65: =J50=J63 -> TRUE | ... L65: =L50=L63 -> TRUE
A67: # | B67: CASH FLOW STATEMENT
B68: OPERATING ACTIVITIES
B69: Profit from operations | C69: =IFERROR(DATA!E4,0) -> 8935 | D69: =IFERROR(DATA!F4,0) -> 10413 | E69: =IFERROR(DATA!G4,0) -> 12036 | F69: =IFERROR(DATA!H4,0) -> 11060 | G69: =IFERROR(DATA!I4,0) -> 7503 | H69: =IFERROR(DATA!J4,0) -> 5531 | I69: =IFERROR(DATA!K4,0) -> 5832 | J69: =IFERROR(DATA!L4,0) -> 11112 | ... L69: =IFERROR(DATA!N4,0) -> 20322
B70: Receivables | C70: =IFERROR(DATA!E5,0) -> -204 | D70: =IFERROR(DATA!F5,0) -> 122 | E70: =IFERROR(DATA!G5,0) -> -262 | F70: =IFERROR(DATA!H5,0) -> -851 | G70: =IFERROR(DATA!I5,0) -> 340 | H70: =IFERROR(DATA!J5,0) -> 696 | I70: =IFERROR(DATA!K5,0) -> -764 | J70: =IFERROR(DATA!L5,0) -> -1258 | ... L70: =IFERROR(DATA!N5,0) -> -1969
B71: Inventory | C71: =IFERROR(DATA!E6,0) -> -450 | D71: =IFERROR(DATA!F6,0) -> -131 | E71: =IFERROR(DATA!G6,0) -> 104 | F71: =IFERROR(DATA!H6,0) -> -162 | G71: =IFERROR(DATA!I6,0) -> 109 | H71: =IFERROR(DATA!J6,0) -> 165 | I71: =IFERROR(DATA!K6,0) -> -483 | J71: =IFERROR(DATA!L6,0) -> -751 | ... L71: =IFERROR(DATA!N6,0) -> -1595
B72: Payables | C72: =IFERROR(DATA!E7,0) -> 1789 | D72: =IFERROR(DATA!F7,0) -> 979 | E72: =IFERROR(DATA!G7,0) -> 2128 | F72: =IFERROR(DATA!H7,0) -> -858 | G72: =IFERROR(DATA!I7,0) -> -2155 | H72: =IFERROR(DATA!J7,0) -> 2680 | I72: =IFERROR(DATA!K7,0) -> -396 | J72: =IFERROR(DATA!L7,0) -> 2008 | ... L72: =IFERROR(DATA!N7,0) -> 3509
B73: Loans Advances | C73: =IFERROR(DATA!E8,0) -> -1 | D73: =IFERROR(DATA!F8,0) -> 1 | E73: =IFERROR(DATA!G8,0) -> 0 | F73: =IFERROR(DATA!H8,0) -> -13 | G73: =IFERROR(DATA!I8,0) -> -1 | H73: =IFERROR(DATA!J8,0) -> -6 | I73: =IFERROR(DATA!K8,0) -> -8 | J73: =IFERROR(DATA!L8,0) -> 1 | ... L73: =IFERROR(DATA!N8,0) -> -10
B74: Other WC items | C74: =IFERROR(DATA!E9,0) -> 325 | D74: =IFERROR(DATA!F9,0) -> 1222 | E74: =IFERROR(DATA!G9,0) -> 839 | F74: =IFERROR(DATA!H9,0) -> 569 | G74: =IFERROR(DATA!I9,0) -> -863 | H74: =IFERROR(DATA!J9,0) -> 801 | I74: =IFERROR(DATA!K9,0) -> -1162 | J74: =IFERROR(DATA!L9,0) -> 374 | ... L74: =IFERROR(DATA!N9,0) -> -313
B75: Working capital changes | C75: =IFERROR(DATA!E10,0) -> 1460 | D75: =IFERROR(DATA!F10,0) -> 2192 | E75: =IFERROR(DATA!G10,0) -> 2808 | F75: =IFERROR(DATA!H10,0) -> -1315 | G75: =IFERROR(DATA!I10,0) -> -2570 | H75: =IFERROR(DATA!J10,0) -> 4336 | I75: =IFERROR(DATA!K10,0) -> -2813 | J75: =IFERROR(DATA!L10,0) -> 373 | ... L75: =IFERROR(DATA!N10,0) -> -378
B76: Direct taxes | C76: =IFERROR(DATA!E11,0) -> -1912 | D76: =IFERROR(DATA!F11,0) -> -2323 | E76: =IFERROR(DATA!G11,0) -> -3056 | F76: =IFERROR(DATA!H11,0) -> -3144 | G76: =IFERROR(DATA!I11,0) -> -1438 | H76: =IFERROR(DATA!J11,0) -> -1011 | I76: =IFERROR(DATA!K11,0) -> -1178 | J76: =IFERROR(DATA!L11,0) -> -2233 | ... L76: =IFERROR(DATA!N11,0) -> -3807
B77: CASH FLOW FROM OPERATING ACTIVITIES | C77: =IFERROR(SUM(C69:C76),0) -> 9942 | D77: =IFERROR(SUM(D69:D76),0) -> 12475 | E77: =IFERROR(SUM(E69:E76),0) -> 14597 | F77: =IFERROR(SUM(F69:F76),0) -> 5286 | G77: =IFERROR(SUM(G69:G76),0) -> 925 | H77: =IFERROR(SUM(H69:H76),0) -> 13192 | I77: =IFERROR(SUM(I69:I76),0) -> -972 | J77: =IFERROR(SUM(J69:J76),0) -> 9626 | ... L77: =IFERROR(SUM(L69:L76),0) -> 15759
B79: INVESTING ACTIVITIES
B80: Fixed assets purchased | C80: =IFERROR(DATA!E13,0) -> -2469 | D80: =IFERROR(DATA!F13,0) -> -3391 | E80: =IFERROR(DATA!G13,0) -> -3912 | F80: =IFERROR(DATA!H13,0) -> -4872 | G80: =IFERROR(DATA!I13,0) -> -3437 | H80: =IFERROR(DATA!J13,0) -> -2370 | I80: =IFERROR(DATA!K13,0) -> -3459 | J80: =IFERROR(DATA!L13,0) -> -6347 | ... L80: =IFERROR(DATA!N13,0) -> -10641
B81: Fixed assets sold | C81: =IFERROR(DATA!E14,0) -> 12 | D81: =IFERROR(DATA!F14,0) -> 16 | E81: =IFERROR(DATA!G14,0) -> 26 | F81: =IFERROR(DATA!H14,0) -> 170 | G81: =IFERROR(DATA!I14,0) -> 37 | H81: =IFERROR(DATA!J14,0) -> 42 | I81: =IFERROR(DATA!K14,0) -> 136 | J81: =IFERROR(DATA!L14,0) -> 100 | ... L81: =IFERROR(DATA!N14,0) -> 38
B82: Investments purchased | C82: =IFERROR(DATA!E15,0) -> -12044 | D82: =IFERROR(DATA!F15,0) -> -17716 | E82: =IFERROR(DATA!G15,0) -> -47069 | F82: =IFERROR(DATA!H15,0) -> -52957 | G82: =IFERROR(DATA!I15,0) -> -44205 | H82: =IFERROR(DATA!J15,0) -> -44869 | I82: =IFERROR(DATA!K15,0) -> -60525 | J82: =IFERROR(DATA!L15,0) -> -66597 | ... L82: =IFERROR(DATA!N15,0) -> -73882
B83: Investments sold | C83: =IFERROR(DATA!E16,0) -> 7378 | D83: =IFERROR(DATA!F16,0) -> 11839 | E83: =IFERROR(DATA!G16,0) -> 42564 | F83: =IFERROR(DATA!H16,0) -> 53986 | G83: =IFERROR(DATA!I16,0) -> 46969 | H83: =IFERROR(DATA!J16,0) -> 42920 | I83: =IFERROR(DATA!K16,0) -> 63579 | J83: =IFERROR(DATA!L16,0) -> 61605 | ... L83: =IFERROR(DATA!N16,0) -> 69795
B84: Interest received | C84: =IFERROR(DATA!E17,0) -> 67 | D84: =IFERROR(DATA!F17,0) -> 36 | E84: =IFERROR(DATA!G17,0) -> 68 | F84: =IFERROR(DATA!H17,0) -> 124 | G84: =IFERROR(DATA!I17,0) -> 96 | H84: =IFERROR(DATA!J17,0) -> 67 | I84: =IFERROR(DATA!K17,0) -> 174 | J84: =IFERROR(DATA!L17,0) -> 194 | ... L84: =IFERROR(DATA!N17,0) -> 444
B85: Dividends received | C85: =IFERROR(DATA!E18,0) -> 11 | D85: =IFERROR(DATA!F18,0) -> 13 | E85: =IFERROR(DATA!G18,0) -> 20 | F85: =IFERROR(DATA!H18,0) -> 9 | G85: =IFERROR(DATA!I18,0) -> 4 | H85: =IFERROR(DATA!J18,0) -> 3 | I85: =IFERROR(DATA!K18,0) -> 3 | J85: =IFERROR(DATA!L18,0) -> 6 | ... L85: =IFERROR(DATA!N18,0) -> 9
B86: Redemp n Canc of Shares | C86: =IFERROR(DATA!E19,0) -> 0 | D86: =IFERROR(DATA!F19,0) -> 22 | E86: =IFERROR(DATA!G19,0) -> 0 | F86: =IFERROR(DATA!H19,0) -> 0 | G86: =IFERROR(DATA!I19,0) -> 0 | H86: =IFERROR(DATA!J19,0) -> 0 | I86: =IFERROR(DATA!K19,0) -> 0 | J86: =IFERROR(DATA!L19,0) -> 0 | ... L86: =IFERROR(DATA!N19,0) -> 0
B87: Acquisition of companies | C87: =IFERROR(DATA!E20,0) -> 0 | D87: =IFERROR(DATA!F20,0) -> 0 | E87: =IFERROR(DATA!G20,0) -> 0 | F87: =IFERROR(DATA!H20,0) -> 0 | G87: =IFERROR(DATA!I20,0) -> -15 | H87: =IFERROR(DATA!J20,0) -> -65 | I87: =IFERROR(DATA!K20,0) -> -146 | J87: =IFERROR(DATA!L20,0) -> 0 | ... L87: =IFERROR(DATA!N20,0) -> -18
B88: Other investing items | C88: =IFERROR(DATA!E21,0) -> -186 | D88: =IFERROR(DATA!F21,0) -> 7 | E88: =IFERROR(DATA!G21,0) -> 0 | F88: =IFERROR(DATA!H21,0) -> 0 | G88: =IFERROR(DATA!I21,0) -> -5 | H88: =IFERROR(DATA!J21,0) -> -3019 | I88: =IFERROR(DATA!K21,0) -> -1 | J88: =IFERROR(DATA!L21,0) -> 3003 | ... L88: =IFERROR(DATA!N21,0) -> -201
B89: CASH FLOW FROM INVESTING ACTIVITIES | C89: =IFERROR(SUM(C80:C88),0) -> -7231 | D89: =IFERROR(SUM(D80:D88),0) -> -9174 | E89: =IFERROR(SUM(E80:E88),0) -> -8303 | F89: =IFERROR(SUM(F80:F88),0) -> -3540 | G89: =IFERROR(SUM(G80:G88),0) -> -556 | H89: =IFERROR(SUM(H80:H88),0) -> -7291 | I89: =IFERROR(SUM(I80:I88),0) -> -239 | J89: =IFERROR(SUM(J80:J88),0) -> -8036 | ... L89: =IFERROR(SUM(L80:L88),0) -> -14456
B91: FINANCING ACTIVITIES
B92: Proceeds from borrowings | C92: =IFERROR(DATA!E25,0) -> -92 | D92: =IFERROR(DATA!F25,0) -> -110 | E92: =IFERROR(DATA!G25,0) -> -346 | F92: =IFERROR(DATA!H25,0) -> -73 | G92: =IFERROR(DATA!I25,0) -> -136 | H92: =IFERROR(DATA!J25,0) -> -102 | I92: =IFERROR(DATA!K25,0) -> -130 | J92: =IFERROR(DATA!L25,0) -> -186 | ... L92: =IFERROR(DATA!N25,0) -> -167
B93: Repayment of borrowings | C93: =IFERROR(DATA!E26,0) -> -755 | D93: =IFERROR(DATA!F26,0) -> -1057 | E93: =IFERROR(DATA!G26,0) -> -2266 | F93: =IFERROR(DATA!H26,0) -> -2417 | G93: =IFERROR(DATA!I26,0) -> -2417 | H93: =IFERROR(DATA!J26,0) -> -1812 | I93: =IFERROR(DATA!K26,0) -> -1359 | J93: =IFERROR(DATA!L26,0) -> -1812 | ... L93: =IFERROR(DATA!N26,0) -> -3930
B94: Interest paid fin | C94: =IFERROR(DATA!E27,0) -> 0 | D94: =IFERROR(DATA!F27,0) -> 0 | E94: =IFERROR(DATA!G27,0) -> 0 | F94: =IFERROR(DATA!H27,0) -> 0 | G94: =IFERROR(DATA!I27,0) -> -10 | H94: =IFERROR(DATA!J27,0) -> -11 | I94: =IFERROR(DATA!K27,0) -> -8 | J94: =IFERROR(DATA!L27,0) -> -46 | ... L94: =IFERROR(DATA!N27,0) -> -25
B95: Dividends paid | C95: =IFERROR(DATA!E28,0) -> -154 | D95: =IFERROR(DATA!F28,0) -> -215 | E95: =IFERROR(DATA!G28,0) -> -461 | F95: =IFERROR(DATA!H28,0) -> -497 | G95: =IFERROR(DATA!I28,0) -> -497 | H95: =IFERROR(DATA!J28,0) -> 0 | I95: =IFERROR(DATA!K28,0) -> 0 | J95: =IFERROR(DATA!L28,0) -> 0 | ... L95: =IFERROR(DATA!N28,0) -> 0
B96: Financial liabilities | C96: =IFERROR(DATA!E29,0) -> 16 | D96: =IFERROR(DATA!F29,0) -> -20 | E96: =IFERROR(DATA!G29,0) -> 50 | F96: =IFERROR(DATA!H29,0) -> 113 | G96: =IFERROR(DATA!I29,0) -> -165 | H96: =IFERROR(DATA!J29,0) -> 20 | I96: =IFERROR(DATA!K29,0) -> -6 | J96: =IFERROR(DATA!L29,0) -> 2 | ... L96: =IFERROR(DATA!N29,0) -> -2475
B97: Other financing items | C97: =IFERROR(DATA!E30,0) -> 0 | D97: =IFERROR(DATA!F30,0) -> 0 | E97: =IFERROR(DATA!G30,0) -> 0 | F97: =IFERROR(DATA!H30,0) -> 0 | G97: =IFERROR(DATA!I30,0) -> 0 | H97: =IFERROR(DATA!J30,0) -> 0 | I97: =IFERROR(DATA!K30,0) -> 0 | J97: =IFERROR(DATA!L30,0) -> 0 | ... L97: =IFERROR(DATA!N30,0) -> 0
B98: CASH FLOW FORM FINANCING ACTIVITY | C98: =IFERROR(SUM(C92:C97),0) -> -985 | D98: =IFERROR(SUM(D92:D97),0) -> -1402 | E98: =IFERROR(SUM(E92:E97),0) -> -3023 | F98: =IFERROR(SUM(F92:F97),0) -> -2874 | G98: =IFERROR(SUM(G92:G97),0) -> -3225 | H98: =IFERROR(SUM(H92:H97),0) -> -1905 | I98: =IFERROR(SUM(I92:I97),0) -> -1503 | J98: =IFERROR(SUM(J92:J97),0) -> -2042 | ... L98: =IFERROR(SUM(L92:L97),0) -> -6597
B100: NET CASHFLOW | C100: =IFERROR(C77+C89+C98,0) -> 1726 | D100: =IFERROR(D77+D89+D98,0) -> 1899 | E100: =IFERROR(E77+E89+E98,0) -> 3271 | F100: =IFERROR(F77+F89+F98,0) -> -1128 | G100: =IFERROR(G77+G89+G98,0) -> -2856 | H100: =IFERROR(H77+H89+H98,0) -> 3996 | I100: =IFERROR(I77+I89+I98,0) -> -2714 | J100: =IFERROR(J77+J89+J98,0) -> -452 | ... L100: =IFERROR(L77+L89+L98,0) -> -5294

Sheet RATIO ANALYSIS
B2: ="RATIO ANALYSIS - "&'Data Sheet'!B1 -> RATIO ANALYSIS - MARUTI SUZUKI INDIA LTD
B3: YEARS | C3: ='Data Sheet'!B16 -> 42460 | D3: ='Data Sheet'!C16 -> 42825 | E3: ='Data Sheet'!D16 -> 43190 | F3: ='Data Sheet'!E16 -> 43555 | G3: ='Data Sheet'!F16 -> 43921 | H3: ='Data Sheet'!G16 -> 44286 | I3: ='Data Sheet'!H16 -> 44651 | J3: ='Data Sheet'!I16 -> 45016 | ... L3: ='Data Sheet'!K16 -> 45747 | M3: TREND | N3: MEAN | O3: MEDIAN
B5: Sales Growth | C5: - | D5: =IFERROR(HISTORIACLFINANCIALS!D6,0) -> 0.18225703 | E5: =IFERROR(HISTORIACLFINANCIALS!E6,0) -> 0.17220239 | F5: =IFERROR(HISTORIACLFINANCIALS!F6,0) -> 0.078425599 | G5: =IFERROR(HISTORIACLFINANCIALS!G6,0) -> -0.12093275 | H5: =IFERROR(HISTORIACLFINANCIALS!H6,0) -> -0.06989162 | I5: =IFERROR(HISTORIACLFINANCIALS!I6,0) -> 0.25518388 | J5: =IFERROR(HISTORIACLFINANCIALS!J6,0) -> 0.33104909 | K5: =IFERROR(HISTORIACLFINANCIALS!K6,0) -> 0.20657167 | L5: =IFERROR(HISTORIACLFINANCIALS!L6,0) -> 0.077928523 | N5: =IFERROR(AVERAGE(D5:L5),0) -> 0.12364376 | O5: =IFERROR(MEDIAN(D5:L5),0) -> 0.17220239
B6: EBITDA Growth | D6: =IFERROR(HISTORIACLFINANCIALS!D17/HISTORIACLFINANCIALS!C17-1,0) -> 0.15482984 | E6: =IFERROR(HISTORIACLFINANCIALS!E17/HISTORIACLFINANCIALS!D17-1,0) -> 0.16280119 | F6: =IFERROR(HISTORIACLFINANCIALS!F17/HISTORIACLFINANCIALS!E17-1,0) -> -0.087605938 | G6: =IFERROR(HISTORIACLFINANCIALS!G17/HISTORIACLFINANCIALS!F17-1,0) -> -0.33476841 | H6: =IFERROR(HISTORIACLFINANCIALS!H17/HISTORIACLFINANCIALS!G17-1,0) -> -0.26436438 | I6: =IFERROR(HISTORIACLFINANCIALS!I17/HISTORIACLFINANCIALS!H17-1,0) -> 0.063098362 | J6: =IFERROR(HISTORIACLFINANCIALS!J17/HISTORIACLFINANCIALS!I17-1,0) -> 0.9174548 | K6: =IFERROR(HISTORIACLFINANCIALS!K17/HISTORIACLFINANCIALS!J17-1,0) -> 0.68881696 | L6: =IFERROR(HISTORIACLFINANCIALS!L17/HISTORIACLFINANCIALS!K17-1,0) -> 0.085755088 | N6: =IFERROR(AVERAGE(D6:L6),0) -> 0.15400195 | O6: =IFERROR(MEDIAN(D6:L6),0) -> 0.085755088
B7: EBIT Growth | D7: =IFERROR(HISTORIACLFINANCIALS!D26/HISTORIACLFINANCIALS!C26-1,0) -> 0.19334289 | E7: =IFERROR(HISTORIACLFINANCIALS!E26/HISTORIACLFINANCIALS!D26-1,0) -> 0.18737845 | F7: =IFERROR(HISTORIACLFINANCIALS!F26/HISTORIACLFINANCIALS!E26-1,0) -> -0.17249453 | G7: =IFERROR(HISTORIACLFINANCIALS!G26/HISTORIACLFINANCIALS!F26-1,0) -> -0.42601522 | H7: =IFERROR(HISTORIACLFINANCIALS!H26/HISTORIACLFINANCIALS!G26-1,0) -> -0.39327455 | I7: =IFERROR(HISTORIACLFINANCIALS!I26/HISTORIACLFINANCIALS!H26-1,0) -> 0.11622673 | J7: =IFERROR(HISTORIACLFINANCIALS!J26/HISTORIACLFINANCIALS!I26-1,0) -> 0.97293511 | K7: =IFERROR(HISTORIACLFINANCIALS!K26/HISTORIACLFINANCIALS!J26-1,0) -> 1.2548412 | L7: =IFERROR(HISTORIACLFINANCIALS!L26/HISTORIACLFINANCIALS!K26-1,0) -> 0.55349859 | N7: =IFERROR(AVERAGE(D7:L7),0) -> 0.25404874 | O7: =IFERROR(MEDIAN(D7:L7),0) -> 0.18737845
B8: Net Profit Growth | D8: =IFERROR(HISTORIACLFINANCIALS!D32/HISTORIACLFINANCIALS!C32-1,0) -> 0.16447019 | E8: =IFERROR(HISTORIACLFINANCIALS!E32/HISTORIACLFINANCIALS!D32-1,0) -> 0.15174519 | F8: =IFERROR(HISTORIACLFINANCIALS!F32/HISTORIACLFINANCIALS!E32-1,0) -> -0.21617994 | G8: =IFERROR(HISTORIACLFINANCIALS!G32/HISTORIACLFINANCIALS!F32-1,0) -> -0.36423914 | H8: =IFERROR(HISTORIACLFINANCIALS!H32/HISTORIACLFINANCIALS!G32-1,0) -> -0.41647961 | I8: =IFERROR(HISTORIACLFINANCIALS!I32/HISTORIACLFINANCIALS!H32-1,0) -> 0.24791383 | J8: =IFERROR(HISTORIACLFINANCIALS!J32/HISTORIACLFINANCIALS!I32-1,0) -> 0.73636536 | K8: =IFERROR(HISTORIACLFINANCIALS!K32/HISTORIACLFINANCIALS!J32-1,0) -> 1.4804851 | L8: =IFERROR(HISTORIACLFINANCIALS!L32/HISTORIACLFINANCIALS!K32-1,0) -> 0.66308441 | N8: =IFERROR(AVERAGE(D8:L8),0) -> 0.27190726 | O8: =IFERROR(MEDIAN(D8:L8),0) -> 0.16447019
B9: Dividend Growth | D9: =IFERROR(HISTORIACLFINANCIALS!D40/HISTORIACLFINANCIALS!C40-1,0) -> 1.1428571 | E9: =IFERROR(HISTORIACLFINANCIALS!E40/HISTORIACLFINANCIALS!D40-1,0) -> 0.066666667 | F9: =IFERROR(HISTORIACLFINANCIALS!F40/HISTORIACLFINANCIALS!E40-1,0) -> 0 | G9: =IFERROR(HISTORIACLFINANCIALS!G40/HISTORIACLFINANCIALS!F40-1,0) -> -0.25 | H9: =IFERROR(HISTORIACLFINANCIALS!H40/HISTORIACLFINANCIALS!G40-1,0) -> -0.25 | I9: =IFERROR(HISTORIACLFINANCIALS!I40/HISTORIACLFINANCIALS!H40-1,0) -> 0.33333333 | J9: =IFERROR(HISTORIACLFINANCIALS!J40/HISTORIACLFINANCIALS!I40-1,0) -> 0.5 | K9: =IFERROR(HISTORIACLFINANCIALS!K40/HISTORIACLFINANCIALS!J40-1,0) -> 0.38934879 | L9: =IFERROR(HISTORIACLFINANCIALS!L40/HISTORIACLFINANCIALS!K40-1,0) -> 0.08 | N9: =IFERROR(AVERAGE(D9:L9),0) -> 0.22357844 | O9: =IFERROR(MEDIAN(D9:L9),0) -> 0.08
B11: Gross Margin | C11: =HISTORIACLFINANCIALS!C12 -> 0.27367726 | D11: =HISTORIACLFINANCIALS!D12 -> 0.2655651 | E11: =HISTORIACLFINANCIALS!E12 -> 0.26092666 | F11: =HISTORIACLFINANCIALS!F12 -> 0.25428932 | G11: =HISTORIACLFINANCIALS!G12 -> 0.23794475 | H11: =HISTORIACLFINANCIALS!H12 -> 0.21253339 | I11: =HISTORIACLFINANCIALS!I12 -> 0.18964155 | J11: =HISTORIACLFINANCIALS!J12 -> 0.2107249 | ... L11: =HISTORIACLFINANCIALS!L12 -> 0.23117197 | N11: =IFERROR(AVERAGE(C11:L11),0) -> 0.23750441 | O11: =IFERROR(MEDIAN(C11:L11),0) -> 0.23825699
B12: EBITDA Margin | C12: =HISTORIACLFINANCIALS!C18 -> 0.15669833 | D12: =HISTORIACLFINANCIALS!D18 -> 0.15306308 | E12: =HISTORIACLFINANCIALS!E18 -> 0.1518355 | F12: =HISTORIACLFINANCIALS!F18 -> 0.12845931 | G12: =HISTORIACLFINANCIALS!G18 -> 0.097211208 | H12: =HISTORIACLFINANCIALS!H18 -> 0.076885693 | I12: =HISTORIACLFINANCIALS!I18 -> 0.065119586 | J12: =HISTORIACLFINANCIALS!J18 -> 0.093808608 | ... L12: =HISTORIACLFINANCIALS!L18 -> 0.1322556 | N12: =IFERROR(AVERAGE(C12:L12),0) -> 0.11866392 | O12: =IFERROR(MEDIAN(C12:L12),0) -> 0.12988078
B13: EBIT Margin | C13: =IFERROR(HISTORIACLFINANCIALS!C17-HISTORIACLFINANCIALS!C23,0)/HISTORIACLFINANCIALS!C5-1 -> -0.8885169 | D13: =IFERROR(HISTORIACLFINANCIALS!D17-HISTORIACLFINANCIALS!D23,0)/HISTORIACLFINANCIALS!D5-1 -> -0.88747154 | E13: =IFERROR(HISTORIACLFINANCIALS!E17-HISTORIACLFINANCIALS!E23,0)/HISTORIACLFINANCIALS!E5-1 -> -0.88601468 | F13: =IFERROR(HISTORIACLFINANCIALS!F17-HISTORIACLFINANCIALS!F23,0)/HISTORIACLFINANCIALS!F5-1 -> -0.91253595 | G13: =IFERROR(HISTORIACLFINANCIALS!G17-HISTORIACLFINANCIALS!G23,0)/HISTORIACLFINANCIALS!G5-1 -> -0.94289056 | H13: =IFERROR(HISTORIACLFINANCIALS!H17-HISTORIACLFINANCIALS!H23,0)/HISTORIACLFINANCIALS!H5-1 -> -0.96274655 | I13: =IFERROR(HISTORIACLFINANCIALS!I17-HISTORIACLFINANCIALS!I23,0)/HISTORIACLFINANCIALS!I5-1 -> -0.96687075 | J13: =IFERROR(HISTORIACLFINANCIALS!J17-HISTORIACLFINANCIALS!J23,0)/HISTORIACLFINANCIALS!J5-1 -> -0.95089448 | ... L13: =IFERROR(HISTORIACLFINANCIALS!L17-HISTORIACLFINANCIALS!L23,0)/HISTORIACLFINANCIALS!L5-1 -> -0.8677444 | N13: =IFERROR(AVERAGE(C13:L13),0) -> -0.91739174 | O13: =IFERROR(MEDIAN(C13:L13),0) -> -0.91038377
B14: EBT Margin | C14: =HISTORIACLFINANCIALS!C27 -> 0.1114831 | D14: =HISTORIACLFINANCIALS!D27 -> 0.11252846 | E14: =HISTORIACLFINANCIALS!E27 -> 0.11398532 | F14: =HISTORIACLFINANCIALS!F27 -> 0.087464055 | G14: =HISTORIACLFINANCIALS!G27 -> 0.057109437 | H14: =HISTORIACLFINANCIALS!H27 -> 0.037253453 | I14: =HISTORIACLFINANCIALS!I27 -> 0.03312925 | J14: =HISTORIACLFINANCIALS!J27 -> 0.049105522 | ... L14: =HISTORIACLFINANCIALS!L27 -> 0.1322556 | N14: =IFERROR(AVERAGE(C14:L14),0) -> 0.082608258 | O14: =IFERROR(MEDIAN(C14:L14),0) -> 0.089616227
B15: Net Profit Margin | C15: =HISTORIACLFINANCIALS!C33 -> 0.075234854 | D15: =HISTORIACLFINANCIALS!D33 -> 0.07410296 | E15: =HISTORIACLFINANCIALS!E33 -> 0.072809719 | F15: =HISTORIACLFINANCIALS!F33 -> 0.052919477 | G15: =HISTORIACLFINANCIALS!G33 -> 0.038272535 | H15: =HISTORIACLFINANCIALS!H33 -> 0.02401097 | I15: =HISTORIACLFINANCIALS!I33 -> 0.023871898 | J15: =HISTORIACLFINANCIALS!J33 -> 0.031141103 | ... L15: =HISTORIACLFINANCIALS!L33 -> 0.098773813 | N15: =IFERROR(AVERAGE(C15:L15),0) -> 0.05551576 | O15: =IFERROR(MEDIAN(C15:L15),0) -> 0.058469873
B17: SalesExpenses%Sales | C17: =HISTORIACLFINANCIALS!C15 -> 0.11697894 | D17: =HISTORIACLFINANCIALS!D15 -> 0.11250202 | E17: =HISTORIACLFINANCIALS!E15 -> 0.10909116 | F17: =HISTORIACLFINANCIALS!F15 -> 0.12583001 | G17: =HISTORIACLFINANCIALS!G15 -> 0.14073354 | H17: =HISTORIACLFINANCIALS!H15 -> 0.1356477 | I17: =HISTORIACLFINANCIALS!I15 -> 0.12452196 | J17: =HISTORIACLFINANCIALS!J15 -> 0.11691629 | ... L17: =HISTORIACLFINANCIALS!L15 -> 0.098916377 | N17: =IFERROR(AVERAGE(C17:L17),0) -> 0.1188405 | O17: =IFERROR(MEDIAN(C17:L17),0) -> 0.11694761
B18: Depreciation%Sales | C18: =HISTORIACLFINANCIALS!C24 -> 0.045215232 | D18: =HISTORIACLFINANCIALS!D24 -> 0.040534626 | E18: =HISTORIACLFINANCIALS!E24 -> 0.037850178 | F18: =HISTORIACLFINANCIALS!F24 -> 0.040995254 | G18: =HISTORIACLFINANCIALS!G24 -> 0.040101771 | H18: =HISTORIACLFINANCIALS!H24 -> 0.03963224 | I18: =HISTORIACLFINANCIALS!I24 -> 0.031990336 | J18: =HISTORIACLFINANCIALS!J24 -> 0.044703087 | ... L18: =HISTORIACLFINANCIALS!L24 -> 0 | N18: =IFERROR(AVERAGE(C18:L18),0) -> 0.036055657 | O18: =IFERROR(MEDIAN(C18:L18),0) -> 0.039867006
B19: Operating%Sales | C19: =C13 -> -0.8885169 | D19: =D13 -> -0.88747154 | E19: =E13 -> -0.88601468 | F19: =F13 -> -0.91253595 | G19: =G13 -> -0.94289056 | H19: =H13 -> -0.96274655 | I19: =I13 -> -0.96687075 | J19: =J13 -> -0.95089448 | ... L19: =L13 -> -0.8677444 | N19: =IFERROR(AVERAGE(C19:L19),0) -> -0.91739174 | O19: =IFERROR(MEDIAN(C19:L19),0) -> -0.91038377
B21: Return on Capital Employeed | C21: =IFERROR(HISTORIACLFINANCIALS!C17-HISTORIACLFINANCIALS!C23,0)/(SUM(HISTORIACLFINANCIALS!C46:C48)) -> 0.20813113 | D21: =IFERROR(HISTORIACLFINANCIALS!D17-HISTORIACLFINANCIALS!D23,0)/(SUM(HISTORIACLFINANCIALS!D46:D48)) -> 0.20398736 | E21: =IFERROR(HISTORIACLFINANCIALS!E17-HISTORIACLFINANCIALS!E23,0)/(SUM(HISTORIACLFINANCIALS!E46:E48)) -> 0.21314567 | F21: =IFERROR(HISTORIACLFINANCIALS!F17-HISTORIACLFINANCIALS!F23,0)/(SUM(HISTORIACLFINANCIALS!F46:F48)) -> 0.1593149 | G21: =IFERROR(HISTORIACLFINANCIALS!G17-HISTORIACLFINANCIALS!G23,0)/(SUM(HISTORIACLFINANCIALS!G46:G48)) -> 0.087120013 | H21: =IFERROR(HISTORIACLFINANCIALS!H17-HISTORIACLFINANCIALS!H23,0)/(SUM(HISTORIACLFINANCIALS!H46:H48)) -> 0.04942545 | I21: =IFERROR(HISTORIACLFINANCIALS!I17-HISTORIACLFINANCIALS!I23,0)/(SUM(HISTORIACLFINANCIALS!I46:I48)) -> 0.052481214 | J21: =IFERROR(HISTORIACLFINANCIALS!J17-HISTORIACLFINANCIALS!J23,0)/(SUM(HISTORIACLFINANCIALS!J46:J48)) -> 0.091585156 | ... L21: =IFERROR(HISTORIACLFINANCIALS!L17-HISTORIACLFINANCIALS!L23,0)/(SUM(HISTORIACLFINANCIALS!L46:L48)) -> 0.20994758 | N21: =IFERROR(AVERAGE(C21:L21),0) -> 0.14269449 | O21: =IFERROR(MEDIAN(C21:L21),0) -> 0.15556067
B22: Retained Earning% | C22: =HISTORIACLFINANCIALS!C43 -> 0.75604127 | D22: =HISTORIACLFINANCIALS!D43 -> 0.55106733 | E22: =HISTORIACLFINANCIALS!E43 -> 0.58422964 | F22: =HISTORIACLFINANCIALS!F43 -> 0.46955892 | G22: =HISTORIACLFINANCIALS!G43 -> 0.37424457 | H22: =HISTORIACLFINANCIALS!H43 -> 0.19571522 | I22: =HISTORIACLFINANCIALS!I43 -> 0.14066205 | J22: =HISTORIACLFINANCIALS!J43 -> 0.25764073 | ... L22: =HISTORIACLFINANCIALS!L43 -> 0.71898463 | N22: =IFERROR(AVERAGE(C22:L22),0) -> 0.46154107 | O22: =IFERROR(MEDIAN(C22:L22),0) -> 0.51031312
B23: Return on equity% | C23: =IFERROR(HISTORIACLFINANCIALS!C32,0)/SUM(HISTORIACLFINANCIALS!C46:C47) -> 0.14151751 | D23: =IFERROR(HISTORIACLFINANCIALS!D32,0)/SUM(HISTORIACLFINANCIALS!D46:D47) -> 0.13608325 | E23: =IFERROR(HISTORIACLFINANCIALS!E32,0)/SUM(HISTORIACLFINANCIALS!E46:E47) -> 0.13653623 | F23: =IFERROR(HISTORIACLFINANCIALS!F32,0)/SUM(HISTORIACLFINANCIALS!F46:F47) -> 0.096718983 | G23: =IFERROR(HISTORIACLFINANCIALS!G32,0)/SUM(HISTORIACLFINANCIALS!G46:G47) -> 0.058601987 | H23: =IFERROR(HISTORIACLFINANCIALS!H32,0)/SUM(HISTORIACLFINANCIALS!H46:H47) -> 0.032184394 | I23: =IFERROR(HISTORIACLFINANCIALS!I32,0)/SUM(HISTORIACLFINANCIALS!I46:I47) -> 0.038107114 | J23: =IFERROR(HISTORIACLFINANCIALS!J32,0)/SUM(HISTORIACLFINANCIALS!J46:J47) -> 0.059252678 | ... L23: =IFERROR(HISTORIACLFINANCIALS!L32,0)/SUM(HISTORIACLFINANCIALS!L46:L47) -> 0.15693907 | N23: =IFERROR(AVERAGE(C23:L23),0) -> 0.09619924 | O23: =IFERROR(MEDIAN(C23:L23),0) -> 0.10138509
B24: Self Sustained Growth Rate | C24: =IFERROR(C22*C23,0) -> 0.10699308 | D24: =IFERROR(D22*D23,0) -> 0.074991032 | E24: =IFERROR(E22*E23,0) -> 0.079768512 | F24: =IFERROR(F22*F23,0) -> 0.045415261 | G24: =IFERROR(G22*G23,0) -> 0.021931476 | H24: =IFERROR(H22*H23,0) -> 0.0062989756 | I24: =IFERROR(I22*I23,0) -> 0.0053602248 | J24: =IFERROR(J22*J23,0) -> 0.015265903 | ... L24: =IFERROR(L22*L23,0) -> 0.11283678 | N24: =IFERROR(AVERAGE(C24:L24),0) -> 0.052902051 | O24: =IFERROR(MEDIAN(C24:L24),0) -> 0.05278727
B25: Interest Coverage Ratio | C25: =IFERROR(HISTORIACLFINANCIALS!C17-HISTORIACLFINANCIALS!C23,0)/HISTORIACLFINANCIALS!C20 -> 78.582619 | D25: =IFERROR(HISTORIACLFINANCIALS!D17-HISTORIACLFINANCIALS!D23,0)/HISTORIACLFINANCIALS!D20 -> 85.699105 | E25: =IFERROR(HISTORIACLFINANCIALS!E17-HISTORIACLFINANCIALS!E23,0)/HISTORIACLFINANCIALS!E20 -> 26.307403 | F25: =IFERROR(HISTORIACLFINANCIALS!F17-HISTORIACLFINANCIALS!F23,0)/HISTORIACLFINANCIALS!F20 -> 99.181818 | G25: =IFERROR(HISTORIACLFINANCIALS!G17-HISTORIACLFINANCIALS!G23,0)/HISTORIACLFINANCIALS!G20 -> 32.197466 | H25: =IFERROR(HISTORIACLFINANCIALS!H17-HISTORIACLFINANCIALS!H23,0)/HISTORIACLFINANCIALS!H20 -> 25.752456 | I25: =IFERROR(HISTORIACLFINANCIALS!I17-HISTORIACLFINANCIALS!I23,0)/HISTORIACLFINANCIALS!I20 -> 23.114534 | J25: =IFERROR(HISTORIACLFINANCIALS!J17-HISTORIACLFINANCIALS!J23,0)/HISTORIACLFINANCIALS!J20 -> 30.873797 | ... L25: =IFERROR(HISTORIACLFINANCIALS!L17-HISTORIACLFINANCIALS!L23,0)/HISTORIACLFINANCIALS!L20 -> 104.138 | N25: =IFERROR(AVERAGE(C25:L25),0) -> 57.308945 | O25: =IFERROR(MEDIAN(C25:L25),0) -> 49.719859
B27: Debtor Turnover Ratio | C27: =IFERROR(HISTORIACLFINANCIALS!C5/HISTORIACLFINANCIALS!C58,0) -> 43.515944 | D27: =IFERROR(HISTORIACLFINANCIALS!D5/HISTORIACLFINANCIALS!D58,0) -> 56.614835 | E27: =IFERROR(HISTORIACLFINANCIALS!E5/HISTORIACLFINANCIALS!E58,0) -> 54.462536 | F27: =IFERROR(HISTORIACLFINANCIALS!F5/HISTORIACLFINANCIALS!F58,0) -> 37.213983 | G27: =IFERROR(HISTORIACLFINANCIALS!G5/HISTORIACLFINANCIALS!G58,0) -> 38.256561 | H27: =IFERROR(HISTORIACLFINANCIALS!H5/HISTORIACLFINANCIALS!H58,0) -> 54.982421 | I27: =IFERROR(HISTORIACLFINANCIALS!I5/HISTORIACLFINANCIALS!I58,0) -> 43.415974 | J27: =IFERROR(HISTORIACLFINANCIALS!J5/HISTORIACLFINANCIALS!J58,0) -> 35.612558 | ... L27: =IFERROR(HISTORIACLFINANCIALS!L5/HISTORIACLFINANCIALS!L58,0) -> 23.382265 | N27: =IFERROR(AVERAGE(C27:L27),0) -> 41.831728 | O27: =IFERROR(MEDIAN(C27:L27),0) -> 40.836268
B28: Creditor Turnover Ratio | C28: =IFERROR(HISTORIACLFINANCIALS!C5/HISTORIACLFINANCIALS!C72,0) -> 32.190609 | D28: =IFERROR(HISTORIACLFINANCIALS!D5/HISTORIACLFINANCIALS!D72,0) -> 69.545455 | E28: =IFERROR(HISTORIACLFINANCIALS!E5/HISTORIACLFINANCIALS!E72,0) -> 37.504417 | F28: =IFERROR(HISTORIACLFINANCIALS!F5/HISTORIACLFINANCIALS!F72,0) -> -100.31294 | G28: =IFERROR(HISTORIACLFINANCIALS!G5/HISTORIACLFINANCIALS!G72,0) -> -35.109049 | H28: =IFERROR(HISTORIACLFINANCIALS!H5/HISTORIACLFINANCIALS!H72,0) -> 26.258209 | I28: =IFERROR(HISTORIACLFINANCIALS!I5/HISTORIACLFINANCIALS!I72,0) -> -223.05505 | J28: =IFERROR(HISTORIACLFINANCIALS!J5/HISTORIACLFINANCIALS!J72,0) -> 58.551444 | ... L28: =IFERROR(HISTORIACLFINANCIALS!L5/HISTORIACLFINANCIALS!L72,0) -> 43.577372 | N28: =IFERROR(AVERAGE(C28:L28),0) -> -4.8134022 | O28: =IFERROR(MEDIAN(C28:L28),0) -> 34.847513
B29: Inventory Turnover Ratio | C29: =IFERROR(HISTORIACLFINANCIALS!C8/HISTORIACLFINANCIALS!C59,0) -> 13.352551 | D29: =IFERROR(HISTORIACLFINANCIALS!D8/HISTORIACLFINANCIALS!D59,0) -> 15.321261 | E29: =IFERROR(HISTORIACLFINANCIALS!E8/HISTORIACLFINANCIALS!E59,0) -> 18.664958 | F29: =IFERROR(HISTORIACLFINANCIALS!F8/HISTORIACLFINANCIALS!F59,0) -> 19.31686 | G29: =IFERROR(HISTORIACLFINANCIALS!G8/HISTORIACLFINANCIALS!G59,0) -> 17.939917 | H29: =IFERROR(HISTORIACLFINANCIALS!H8/HISTORIACLFINANCIALS!H59,0) -> 18.175008 | I29: =IFERROR(HISTORIACLFINANCIALS!I8/HISTORIACLFINANCIALS!I59,0) -> 20.264077 | J29: =IFERROR(HISTORIACLFINANCIALS!J8/HISTORIACLFINANCIALS!J59,0) -> 21.663616 | ... L29: =IFERROR(HISTORIACLFINANCIALS!L8/HISTORIACLFINANCIALS!L59,0) -> 17.005699 | N29: =IFERROR(AVERAGE(C29:L29),0) -> 18.201481 | O29: =IFERROR(MEDIAN(C29:L29),0) -> 18.419983
B30: Fixed Asset Turnover | C30: =IFERROR(HISTORIACLFINANCIALS!C5/HISTORIACLFINANCIALS!C52,0) -> 4.5962361 | D30: =IFERROR(HISTORIACLFINANCIALS!D5/HISTORIACLFINANCIALS!D52,0) -> 5.1150578 | E30: =IFERROR(HISTORIACLFINANCIALS!E5/HISTORIACLFINANCIALS!E52,0) -> 5.9609076 | F30: =IFERROR(HISTORIACLFINANCIALS!F5/HISTORIACLFINANCIALS!F52,0) -> 5.5753597 | G30: =IFERROR(HISTORIACLFINANCIALS!G5/HISTORIACLFINANCIALS!G52,0) -> 4.8055182 | H30: =IFERROR(HISTORIACLFINANCIALS!H5/HISTORIACLFINANCIALS!H52,0) -> 4.6950036 | I30: =IFERROR(HISTORIACLFINANCIALS!I5/HISTORIACLFINANCIALS!I52,0) -> 6.4252939 | J30: =IFERROR(HISTORIACLFINANCIALS!J5/HISTORIACLFINANCIALS!J52,0) -> 6.5938678 | ... L30: =IFERROR(HISTORIACLFINANCIALS!L5/HISTORIACLFINANCIALS!L52,0) -> 4.6361577 | N30: =IFERROR(AVERAGE(C30:L30),0) -> 5.3494349 | O30: =IFERROR(MEDIAN(C30:L30),0) -> 5.103002
B31: Capital Turnover Ratio | C31: =IFERROR(HISTORIACLFINANCIALS!C5/SUM(HISTORIACLFINANCIALS!C46:C48),0) -> 1.8669299 | D31: =IFERROR(HISTORIACLFINANCIALS!D5/SUM(HISTORIACLFINANCIALS!D46:D48),0) -> 1.8127624 | E31: =IFERROR(HISTORIACLFINANCIALS!E5/SUM(HISTORIACLFINANCIALS!E46:E48),0) -> 1.8699397 | F31: =IFERROR(HISTORIACLFINANCIALS!F5/SUM(HISTORIACLFINANCIALS!F46:F48),0) -> 1.82149 | G31: =IFERROR(HISTORIACLFINANCIALS!G5/SUM(HISTORIACLFINANCIALS!G46:G48),0) -> 1.5254924 | H31: =IFERROR(HISTORIACLFINANCIALS!H5/SUM(HISTORIACLFINANCIALS!H46:H48),0) -> 1.3267347 | I31: =IFERROR(HISTORIACLFINANCIALS!I5/SUM(HISTORIACLFINANCIALS!I46:I48),0) -> 1.5841353 | J31: =IFERROR(HISTORIACLFINANCIALS!J5/SUM(HISTORIACLFINANCIALS!J46:J48),0) -> 1.8650684 | ... L31: =IFERROR(HISTORIACLFINANCIALS!L5/SUM(HISTORIACLFINANCIALS!L46:L48),0) -> 1.5874382 | N31: =IFERROR(AVERAGE(C31:L31),0) -> 1.6914225 | O31: =IFERROR(MEDIAN(C31:L31),0) -> 1.7334984
B33: Debtor Days | C33: =IFERROR(365/C27,0) -> 8.3877303 | D33: =IFERROR(365/D27,0) -> 6.4470735 | E33: =IFERROR(365/E27,0) -> 6.7018547 | F33: =IFERROR(365/F27,0) -> 9.8081412 | G33: =IFERROR(365/G27,0) -> 9.5408472 | H33: =IFERROR(365/H27,0) -> 6.6384855 | I33: =IFERROR(365/I27,0) -> 8.4070438 | J33: =IFERROR(365/J27,0) -> 10.249193 | ... L33: =IFERROR(365/L27,0) -> 15.610121 | N33: =IFERROR(AVERAGE(C33:L33),0) -> 9.361802 | O33: =IFERROR(MEDIAN(C33:L33),0) -> 8.9739455
B34: Payable Days | C34: =IFERROR(365/C28,0) -> 11.338711 | D34: =IFERROR(365/D28,0) -> 5.248366 | E34: =IFERROR(365/E28,0) -> 9.7321869 | F34: =IFERROR(365/F28,0) -> -3.6386134 | G34: =IFERROR(365/G28,0) -> -10.39618 | H34: =IFERROR(365/H28,0) -> 13.900415 | I34: =IFERROR(365/I28,0) -> -1.6363673 | J34: =IFERROR(365/J28,0) -> 6.2338343 | ... L34: =IFERROR(365/L28,0) -> 8.3759066 | N34: =IFERROR(AVERAGE(C34:L34),0) -> 4.7703164 | O34: =IFERROR(MEDIAN(C34:L34),0) -> 7.3048704
B35: Inventory Days | C35: =IFERROR(365/C29,0) -> 27.335601 | D35: =IFERROR(365/D29,0) -> 23.823104 | E35: =IFERROR(365/E29,0) -> 19.555362 | F35: =IFERROR(365/F29,0) -> 18.89541 | G35: =IFERROR(365/G29,0) -> 20.34569 | H35: =IFERROR(365/H29,0) -> 20.082522 | I35: =IFERROR(365/I29,0) -> 18.01217 | J35: =IFERROR(365/J29,0) -> 16.848526 | ... L35: =IFERROR(365/L29,0) -> 21.463393 | N35: =IFERROR(AVERAGE(C35:L35),0) -> 20.433246 | O35: =IFERROR(MEDIAN(C35:L35),0) -> 19.818942
B36: Cash Conversion Cycle | C36: =IFERROR(SUM(C33,C35)-C34,0) -> 24.384621 | D36: =IFERROR(SUM(D33,D35)-D34,0) -> 25.021812 | E36: =IFERROR(SUM(E33,E35)-E34,0) -> 16.525029 | F36: =IFERROR(SUM(F33,F35)-F34,0) -> 32.342165 | G36: =IFERROR(SUM(G33,G35)-G34,0) -> 40.282718 | H36: =IFERROR(SUM(H33,H35)-H34,0) -> 12.820592 | I36: =IFERROR(SUM(I33,I35)-I34,0) -> 28.055581 | J36: =IFERROR(SUM(J33,J35)-J34,0) -> 20.863885 | ... L36: =IFERROR(SUM(L33,L35)-L34,0) -> 28.697608 | N36: =IFERROR(AVERAGE(C36:L36),0) -> 25.024731 | O36: =IFERROR(MEDIAN(C36:L36),0) -> 24.703216
B38: CFO/Sales | C38: =IFERROR(HISTORIACLFINANCIALS!C77/HISTORIACLFINANCIALS!C5,0) -> 0.17263714 | D38: =IFERROR(HISTORIACLFINANCIALS!D77/HISTORIACLFINANCIALS!D5,0) -> 0.18322685 | E38: =IFERROR(HISTORIACLFINANCIALS!E77/HISTORIACLFINANCIALS!E5,0) -> 0.18289826 | F38: =IFERROR(HISTORIACLFINANCIALS!F77/HISTORIACLFINANCIALS!F5,0) -> 0.061416198 | G38: =IFERROR(HISTORIACLFINANCIALS!G77/HISTORIACLFINANCIALS!G5,0) -> 0.012225747 | H38: =IFERROR(HISTORIACLFINANCIALS!H77/HISTORIACLFINANCIALS!H5,0) -> 0.18746092 | I38: =IFERROR(HISTORIACLFINANCIALS!I77/HISTORIACLFINANCIALS!I5,0) -> -0.011004214 | J38: =IFERROR(HISTORIACLFINANCIALS!J77/HISTORIACLFINANCIALS!J5,0) -> 0.081873723 | ... L38: =IFERROR(HISTORIACLFINANCIALS!L77/HISTORIACLFINANCIALS!L5,0) -> 0.1030586 | N38: =IFERROR(AVERAGE(C38:L38),0) -> 0.11043602 | O38: =IFERROR(MEDIAN(C38:L38),0) -> 0.1168128
B39: CFO/Total Asset | C39: =IFERROR(HISTORIACLFINANCIALS!C77/HISTORIACLFINANCIALS!C63,0) -> 0.23269476 | D39: =IFERROR(HISTORIACLFINANCIALS!D77/HISTORIACLFINANCIALS!D63,0) -> 0.24008622 | E39: =IFERROR(HISTORIACLFINANCIALS!E77/HISTORIACLFINANCIALS!E63,0) -> 0.24228029 | F39: =IFERROR(HISTORIACLFINANCIALS!F77/HISTORIACLFINANCIALS!F63,0) -> 0.082634163 | G39: =IFERROR(HISTORIACLFINANCIALS!G77/HISTORIACLFINANCIALS!G63,0) -> 0.014537693 | H39: =IFERROR(HISTORIACLFINANCIALS!H77/HISTORIACLFINANCIALS!H63,0) -> 0.18482377 | I39: =IFERROR(HISTORIACLFINANCIALS!I77/HISTORIACLFINANCIALS!I63,0) -> -0.013019804 | J39: =IFERROR(HISTORIACLFINANCIALS!J77/HISTORIACLFINANCIALS!J63,0) -> 0.11378668 | ... L39: =IFERROR(HISTORIACLFINANCIALS!L77/HISTORIACLFINANCIALS!L63,0) -> 0.11941242 | N39: =IFERROR(AVERAGE(C39:L39),0) -> 0.13778723 | O39: =IFERROR(MEDIAN(C39:L39),0) -> 0.14002425
B40: CFO/Total Debt | C40: =IFERROR(HISTORIACLFINANCIALS!C77/HISTORIACLFINANCIALS!C48,0) -> 43.057601 | D40: =IFERROR(HISTORIACLFINANCIALS!D77/HISTORIACLFINANCIALS!D48,0) -> 25.796112 | E40: =IFERROR(HISTORIACLFINANCIALS!E77/HISTORIACLFINANCIALS!E48,0) -> 120.83609 | F40: =IFERROR(HISTORIACLFINANCIALS!F77/HISTORIACLFINANCIALS!F48,0) -> 33.120301 | G40: =IFERROR(HISTORIACLFINANCIALS!G77/HISTORIACLFINANCIALS!G48,0) -> 5.0244432 | H40: =IFERROR(HISTORIACLFINANCIALS!H77/HISTORIACLFINANCIALS!H48,0) -> 24.388981 | I40: =IFERROR(HISTORIACLFINANCIALS!I77/HISTORIACLFINANCIALS!I48,0) -> -2.2843713 | J40: =IFERROR(HISTORIACLFINANCIALS!J77/HISTORIACLFINANCIALS!J48,0) -> 7.7174697 | ... L40: =IFERROR(HISTORIACLFINANCIALS!L77/HISTORIACLFINANCIALS!L48,0) -> 181.13793 | N40: =IFERROR(AVERAGE(C40:L40),0) -> 59.496657 | O40: =IFERROR(MEDIAN(C40:L40),0) -> 29.458207

Sheet FORECASTING
B3: ='Data Sheet'!B1&" - "&HISTORIACLFINANCIALS!B5 -> MARUTI SUZUKI INDIA LTD - SALES | G3: ='Data Sheet'!B1&" - "&HISTORIACLFINANCIALS!B8 -> MARUTI SUZUKI INDIA LTD - COGS | L3: ='Data Sheet'!B1&" - "&HISTORIACLFINANCIALS!B14 -> MARUTI SUZUKI INDIA LTD - S&G EXPENSES
B4: YEAR WEIGHT | C4: YEAR | D4: SALES | E4: SALES GROWTH | G4: YEAR WEIGHT | H4: YEAR | I4: COGS | J4: COGS GROWTH | L4: YEAR WEIGHT | M4: YEAR | N4: S&G Exp | O4: S&G GROWTH
B5: 1 | C5: =HISTORIACLFINANCIALS!$C$3 -> 42460 | D5: {=TRANSPOSE(HISTORIACLFINANCIALS!C5:L5)} -> 57589 | E5: - | G5: 1 | H5: =HISTORIACLFINANCIALS!$C$3 -> 42460 | I5: {=TRANSPOSE(HISTORIACLFINANCIALS!C8:L8)} -> 41828.2 | J5: - | L5: 1 | M5: =HISTORIACLFINANCIALS!$C$3 -> 42460 | N5: {=TRANSPOSE(HISTORIACLFINANCIALS!C14:L14)} -> 6736.7 | O5: -
B6: =B5+1 -> 2 | C6: =C5+365 -> 42825 | D6: 68085 | E6: =D6/D5-1 -> 0.18225703 | G6: =G5+1 -> 2 | H6: =H5+365 -> 42825 | I6: 50004 | J6: =I6/I5-1 -> 0.19546144 | L6: =L5+1 -> 2 | M6: =M5+365 -> 42825 | N6: 7659.7 | O6: =N6/N5-1 -> 0.1370107
B7: =B6+1 -> 3 | C7: =C6+365 -> 43190 | D7: 79809.4 | E7: =D7/D6-1 -> 0.17220239 | G7: =G6+1 -> 3 | H7: =H6+365 -> 43190 | I7: 58985 | J7: =I7/I6-1 -> 0.17960563 | L7: =L6+1 -> 3 | M7: =M6+365 -> 43190 | N7: 8706.5 | O7: =N7/N6-1 -> 0.13666332
B8: =B7+1 -> 4 | C8: =C7+365 -> 43555 | D8: 86068.5 | E8: =D8/D7-1 -> 0.078425599 | G8: =G7+1 -> 4 | H8: =H7+365 -> 43555 | I8: 64182.2 | J8: =I8/I7-1 -> 0.088110537 | L8: =L7+1 -> 4 | M8: =M7+365 -> 43555 | N8: 10830 | O8: =N8/N7-1 -> 0.24389824
B9: =B8+1 -> 5 | C9: =C8+365 -> 43920 | D9: 75660 | E9: =D9/D8-1 -> -0.12093275 | G9: =G8+1 -> 5 | H9: =H8+365 -> 43920 | I9: 57657.1 | J9: =I9/I8-1 -> -0.10166526 | L9: =L8+1 -> 5 | M9: =M8+365 -> 43920 | N9: 10647.9 | O9: =N9/N8-1 -> -0.016814404
B10: =B9+1 -> 6 | C10: =C9+365 -> 44285 | D10: 70372 | E10: =D10/D9-1 -> -0.06989162 | G10: =G9+1 -> 6 | H10: =H9+365 -> 44285 | I10: 55415.6 | J10: =I10/I9-1 -> -0.038876392 | L10: =L9+1 -> 6 | M10: =M9+365 -> 44285 | N10: 9545.8 | O10: =N10/N9-1 -> -0.10350398
B11: =B10+1 -> 7 | C11: =C10+365 -> 44650 | D11: 88329.8 | E11: =D11/D10-1 -> 0.25518388 | G11: =G10+1 -> 7 | H11: =H10+365 -> 44650 | I11: 71578.8 | J11: =I11/I10-1 -> 0.29167238 | L11: =L10+1 -> 7 | M11: =M10+365 -> 44650 | N11: 10999 | O11: =N11/N10-1 -> 0.15223449
B12: =B11+1 -> 8 | C12: =C11+365 -> 45015 | D12: 117571.3 | E12: =D12/D11-1 -> 0.33104909 | G12: =G11+1 -> 8 | H12: =H11+365 -> 45015 | I12: 92796.1 | J12: =I12/I11-1 -> 0.29641877 | L12: =L11+1 -> 8 | M12: =M11+365 -> 45015 | N12: 13746 | O12: =N12/N11-1 -> 0.24974998
B13: =B12+1 -> 9 | C13: =C12+365 -> 45380 | D13: 141858.2 | E13: =D13/D12-1 -> 0.20657167 | G13: =G12+1 -> 9 | H13: =H12+365 -> 45380 | I13: 108015.2 | J13: =I13/I12-1 -> 0.16400581 | L13: =L12+1 -> 9 | M13: =M12+365 -> 45380 | N13: 15216.7 | O13: =N13/N12-1 -> 0.10699112
B14: =B13+1 -> 10 | C14: =C13+365 -> 45745 | D14: 152913 | E14: =D14/D13-1 -> 0.077928523 | G14: =G13+1 -> 10 | H14: =H13+365 -> 45745 | I14: 117563.8 | J14: =I14/I13-1 -> 0.088400521 | L14: =L13+1 -> 10 | M14: =M13+365 -> 45745 | N14: 15125.6 | O14: =N14/N13-1 -> -0.0059868434
B15: =B14+1 -> 11 | C15: =C14+365 -> 46110 | D15: =FORECAST(B15,_xlfn.ANCHORARRAY($D$5),$B$5:$B$14) -> 145980.08 | E15: =D15/D14-1 -> -0.045338984 | G15: =G14+1 -> 11 | H15: =H14+365 -> 46110 | I15: =FORECAST(G15,_xlfn.ANCHORARRAY($I$5),$G$5:$G$14) -> 114359.35 | J15: =I15/I14-1 -> -0.027257087 | L15: =L14+1 -> 11 | M15: =M14+365 -> 46110 | N15: =FORECAST(L15,_xlfn.ANCHORARRAY($N$5),$L$5:$L$14) -> 16021.44 | O15: =IFERROR(N15/N14-1,0) -> 0.059226741
B16: =B15+1 -> 12 | C16: =C15+365 -> 46475 | D16: =FORECAST(B16,_xlfn.ANCHORARRAY($D$5),$B$5:$B$14) -> 155462.71 | E16: =D16/D15-1 -> 0.064958377 | G16: =G15+1 -> 12 | H16: =H15+365 -> 46475 | I16: =FORECAST(G16,_xlfn.ANCHORARRAY($I$5),$G$5:$G$14) -> 122096.94 | J16: =I16/I15-1 -> 0.067660329 | L16: =L15+1 -> 12 | M16: =M15+365 -> 46475 | N16: =FORECAST(L16,_xlfn.ANCHORARRAY($N$5),$L$5:$L$14) -> 16948.722 | O16: =N16/N15-1 -> 0.057877558
B17: =B16+1 -> 13 | C17: =C16+365 -> 46840 | D17: =FORECAST(B17,_xlfn.ANCHORARRAY($D$5),$B$5:$B$14) -> 164945.34 | E17: =D17/D16-1 -> 0.060996165 | G17: =G16+1 -> 13 | H17: =H16+365 -> 46840 | I17: =FORECAST(G17,_xlfn.ANCHORARRAY($I$5),$G$5:$G$14) -> 129834.54 | J17: =I17/I16-1 -> 0.063372524 | L17: =L16+1 -> 13 | M17: =M16+365 -> 46840 | N17: =FORECAST(L17,_xlfn.ANCHORARRAY($N$5),$L$5:$L$14) -> 17876.004 | O17: =N17/N16-1 -> 0.054711018
B18: =B17+1 -> 14 | C18: =C17+365 -> 47205 | D18: =FORECAST(B18,_xlfn.ANCHORARRAY($D$5),$B$5:$B$14) -> 174427.97 | E18: =D18/D17-1 -> 0.057489525 | G18: =G17+1 -> 14 | H18: =H17+365 -> 47205 | I18: =FORECAST(G18,_xlfn.ANCHORARRAY($I$5),$G$5:$G$14) -> 137572.13 | J18: =I18/I17-1 -> 0.059595788 | L18: =L17+1 -> 14 | M18: =M17+365 -> 47205 | N18: =FORECAST(L18,_xlfn.ANCHORARRAY($N$5),$L$5:$L$14) -> 18803.285 | O18: =N18/N17-1 -> 0.051872993
B19: =B18+1 -> 15 | C19: =C18+365 -> 47570 | D19: =FORECAST(B19,_xlfn.ANCHORARRAY($D$5),$B$5:$B$14) -> 183910.6 | E19: =D19/D18-1 -> 0.054364155 | G19: =G18+1 -> 15 | H19: =H18+365 -> 47570 | I19: =FORECAST(G19,_xlfn.ANCHORARRAY($I$5),$G$5:$G$14) -> 145309.72 | J19: =I19/I18-1 -> 0.056243889 | L19: =L18+1 -> 15 | M19: =M18+365 -> 47570 | N19: =FORECAST(L19,_xlfn.ANCHORARRAY($N$5),$L$5:$L$14) -> 19730.567 | O19: =N19/N18-1 -> 0.049314883
B21: SUMMARY OUTPUT
B24: Multiple R | C24: 0.88345136
B25: R Square | C25: 0.78048631
B26: Adjusted R Square | C26: 0.7530471
B27: Standard Error | C27: 16149.493
B28: Observations | C28: 10
B30: ANOVA
C31: df | D31: SS | E31: MS | F31: F | G31: Significance F
B32: Regression | C32: 1 | D32: 7.418421e+09 | E32: 7.418421e+09 | F32: 28.444196 | G32: 0.00069973879
B33: Residual | C33: 8 | D33: 2.0864491e+09 | E33: 2.6080614e+08
B34: Total | C34: 9 | D34: 9.5048701e+09
C36: Coefficients | D36: Standard Error | E36: t Stat | F36: P-value | G36: Lower 95% | H36: Upper 95% | I36: Lower 95.0% | J36: Upper 95.0%
B37: Intercept | C37: 41671.16 | D37: 11032.204 | E37: 3.7772288 | F37: 0.0054095058 | G37: 16230.851 | H37: 67111.469 | I37: 16230.851 | J37: 67111.469
B38: X Variable 1 | C38: 9482.6291 | D38: 1778.0007 | E38: 5.3333101 | F38: 0.00069973879 | G38: 5382.5521 | H38: 13582.706 | I38: 5382.5521 | J38: 13582.706

Sheet WACC
B2: Weighted Average Cost Of Capital
B4: All Figures are in INR unless stated otherwise
B6: Peer Comps
J7: Debt/ | K7: Debt/ | L7: Leverd | M7: Unlevered
B8: Name of the comp | F8: Country | G8: Total Debt | H8: Total Equity | I8: Tax Rate 1 | J8: Equity | K8: Capital | L8: Beta 2 | M8: Beta 3
B10: ='Data Sheet'!B1 -> MARUTI SUZUKI INDIA LTD | F10: India | G10: =Beta_Comp!F3 -> 99.9 | H10: =Beta_Comp!E3 -> 479055.2 | I10: 0.3 | J10: =G10/H10 -> 0.00020853547 | K10: =G10/(G10+H10) -> 0.00020849199 | L10: =REGRESSION!K14 -> 0.42313972 | M10: =L10/(1+(1-I10)*J10) -> 0.42307797
B11: =Beta_Comp!C4 -> M & M | F11: India | G11: =Beta_Comp!F4 -> 126709.33 | H11: =Beta_Comp!E4 -> 439388.48 | I11: 0.3 | J11: =G11/H11 -> 0.28837654 | K11: =G11/(G11+H11) -> 0.22382939 | L11: 1.72 | M11: =L11/(1+(1-I11)*J11) -> 1.4311108
B12: =Beta_Comp!C5 -> Hyundai Motor I | F12: India | G12: =Beta_Comp!F5 -> 856.56 | H12: =Beta_Comp!E5 -> 177093.33 | I12: 0.3 | J12: =G12/H12 -> 0.0048367717 | K12: =G12/(G12+H12) -> 0.0048134899 | L12: 1.06 | M12: =L12/(1+(1-I12)*J12) -> 1.0564232
B13: =Beta_Comp!C6 -> Tata Motors PVeh | F13: India | G13: =Beta_Comp!F6 -> 67258 | H13: =Beta_Comp!E6 -> 140020.65 | I13: 0.3 | J13: =G13/H13 -> 0.48034344 | K13: =G13/(G13+H13) -> 0.32448108 | L13: 1.02 | M13: =L13/(1+(1-I13)*J13) -> 0.7633357
B14: =Beta_Comp!C7 -> Force Motors | F14: India | G14: =Beta_Comp!F7 -> 0 | H14: =Beta_Comp!E7 -> 31416.16 | I14: 0.3 | J14: =G14/H14 -> 0 | K14: =G14/(G14+H14) -> 0 | L14: 1.47 | M14: =L14/(1+(1-I14)*J14) -> 1.47
H17: Average | I17: =AVERAGE(I10:I14) -> 0.3 | J17: =AVERAGE(J10:J14) -> 0.15475306 | K17: =AVERAGE(K10:K14) -> 0.11066649 | L17: =AVERAGE(L10:L14) -> 1.1386279 | M17: =AVERAGE(M10:M14) -> 1.0287895
H18: Median | I18: =MEDIAN(I10:I14) -> 0.3 | J18: =MEDIAN(J10:J14) -> 0.0048367717 | K18: =MEDIAN(K10:K14) -> 0.0048134899 | L18: =MEDIAN(L10:L14) -> 1.06 | M18: =MEDIAN(M10:M14) -> 1.0564232
B21: Cost Of Debt | I21: Cost Of Equity
B23: Pre-Tax Cost Of Debt | C23: 0.043 | I23: Risk Free Rate | J23: 0.065
B24: Tax Rate | C24: =I14 -> 0.3 | I24: Equity Risk Premium | J24: ='Market Return'!G5-WACC!J23 -> 0.086492308
B25: Post Tax Cost of Rate | C25: =C23*(1-C24) -> 0.0301 | I25: Levered Beta 4 | J25: =J34 -> 1.1484443
I26: Cost Of Equity | J26: =J23+J24*J25 -> 0.1643316
B29: Capital Structure | I29: Leverd Beta
D31: Current | E31: Target | I31: Comps Median Unleverd Beta | J31: =M18 -> 1.0564232
B32: Total Debt | C32: =G10 -> 99.9 | D32: =C32/$C$34 -> 0.00020849199 | E32: =K17 -> 0.11066649 | I32: Target Debt/Equity | J32: =E36 -> 0.12443756
B33: Market Capitalization | C33: =H10 -> 479055.2 | D33: =C33/$C$34 -> 0.99979151 | E33: =E34-E32 -> 0.88933351 | I33: Tax Rate | J33: =I14 -> 0.3
B34: Total Capital | C34: =SUM(C32:C33) -> 479155.1 | D34: =C34/$C$34 -> 1 | E34: 1 | I34: Leverd Beta | J34: =J31*(1+(1-J33)*J32) -> 1.1484443
B36: Target Debt/Equity | D36: =D32/D33 -> 0.00020853547 | E36: =E32/E33 -> 0.12443756
I37: Weighted Average Cost of Capital
I39: Cost Of Equity | J39: =J26 -> 0.1643316
I40: Equity Weight | J40: =E33 -> 0.88933351
I42: Cost of Debt | J42: =C25 -> 0.0301
I43: Debt Weight | J43: =E32 -> 0.11066649
I45: WACC | J45: =(J39*J40)+(J42*J43) -> 0.14947666

Sheet Beta_Comp
B2: S.No. | C2: Name | D2: CMP Rs. | E2: Mar Cap Rs.Cr. | F2: Debt Rs.Cr. | G2: Debt / Eq
B3: 1 | C3: Maruti Suzuki | D3: 15237 | E3: 479055.2 | F3: 99.9 | G3: 0
B4: 2 | C4: M & M | D4: 3533.4 | E4: 439388.48 | F4: 126709.33 | G4: 1.53
B5: 3 | C5: Hyundai Motor I | D5: 2179.5 | E5: 177093.33 | F5: 856.56 | G5: 0.05
B6: 4 | C6: Tata Motors PVeh | D6: 380.25 | E6: 140020.65 | F6: 67258 | G6: 0.61
B7: 5 | C7: Force Motors | D7: 23843 | E7: 31416.16 | F7: 0 | G7: 0

Sheet REGRESSION
B2: Regression Beta - 2 year weekly
M4: Beta 1 | N4: =SLOPE(D9:D566,H9:H566) -> 0.23085296
B5: Maruti Suzuki Weekly Return | G5: NIFTY Return | J5: Beta Drifting
B8: Date | C8: Price | D8: Weekly Return | G8: Closing Price | H8: Weekly Return | J8: Leverd Raw Beta | K8: =N4 -> 0.23085296
B9: 44932 | C9: 9328.3 | D9: - | G9: 17859.45 | H9: - | J9: Raw Beta Weight | K9: 0.75
B10: 44934 | C10: 9716.75 | D10: =C10/C9-1 -> 0.0416421 | G10: 17956.6 | H10: =G10/G9-1 -> 0.0054396972
B11: 44935 | C11: 10331.25 | D11: =C11/C10-1 -> 0.06324131 | G11: 18027.65 | H11: =G11/G10-1 -> 0.0039567624 | J11: Market Beta | K11: 1
B12: 44937 | C12: 10227.75 | D12: =C12/C11-1 -> -0.010018149 | G12: 17604.35 | H12: =G12/G11-1 -> -0.023480598 | J12: Market Beta Weight | K12: 0.25
B13: 44938 | C13: 10585.7 | D13: =C13/C12-1 -> 0.034997922 | G13: 17854.05 | H13: =G13/G12-1 -> 0.014183994
B14: 44962 | C14: 8776.85 | D14: =C14/C13-1 -> -0.17087675 | G14: 17856.5 | H14: =G14/G13-1 -> 0.00013722377 | J14: Adjusted Beta | K14: =(K8*K9)+(K11*K12) -> 0.42313972
B15: 44963 | C15: 9485.35 | D15: =C15/C14-1 -> 0.080723722 | G15: 17944.2 | H15: =G15/G14-1 -> 0.0049113768
B16: 44965 | C16: 9653.8 | D16: =C16/C15-1 -> 0.017758965 | G16: 17465.8 | H16: =G16/G15-1 -> -0.026660425
B17: 44968 | C17: 10303.6 | D17: =C17/C16-1 -> 0.067310282 | G17: 17594.35 | H17: =G17/G16-1 -> 0.007360098
B18: 44989 | C18: 8503.05 | D18: =C18/C17-1 -> -0.1747496 | G18: 17412.9 | H18: =G18/G17-1 -> -0.01031297
B19: 44990 | C19: 8797.3 | D19: =C19/C18-1 -> 0.03460523 | G19: 17100.05 | H19: =G19/G18-1 -> -0.017966565
B20: 44992 | C20: 9673 | D20: =C20/C19-1 -> 0.099541905 | G20: 16945.05 | H20: =G20/G19-1 -> -0.009064301
B21: 44993 | C21: 9543.7 | D21: =C21/C20-1 -> -0.013367104 | G21: 17359.75 | H21: =G21/G20-1 -> 0.024473224
B22: 44995 | C22: 10346.9 | D22: =C22/C21-1 -> 0.084160231 | G22: 17599.15 | H22: =G22/G21-1 -> 0.013790521
B23: 44996 | C23: 10276.3 | D23: =C23/C22-1 -> -0.0068232997 | G23: 17828 | H23: =G23/G22-1 -> 0.013003469
B24: 45002 | C24: 8316.85 | D24: =C24/C23-1 -> -0.19067661 | G24: 17624.05 | H24: =G24/G23-1 -> -0.01143987
B25: 45005 | C25: 8219.6 | D25: =C25/C24-1 -> -0.011693129 | G25: 18065 | H25: =G25/G24-1 -> 0.025019788
B26: 45006 | C26: 8228.4 | D26: =C26/C25-1 -> 0.0010706117 | G26: 18069 | H26: =G26/G25-1 -> 0.00022142264
... B566: 46061 | C566: 15237 | D566: =C566/C565-1 -> 0.016003201 | G566: 22904.45 | H566: =G566/G565-1 -> 0

Sheet Market Return
B1: Return on Market
B2: Year | C2: Annual
B3: 2000 | C3: -0.1465 | F3: Average Return | G3: =AVERAGE(C3:C28) -> 0.15149231
B4: 2001 | C4: -0.1618 | F4: Divedend Yield | G4: 1.28% 1 | H4: # From Prime Investors site
B5: 2002 | C5: 0.0325 | F5: Total Market Return | G5: =SUM(G3:G4) -> 0.15149231
B6: 2003 | C6: 0.719
B7: 2004 | C7: 0.1068
B8: 2005 | C8: 0.3634
B9: 2006 | C9: 0.3983
B10: 2007 | C10: 0.5477
B11: 2008 | C11: -0.5179
B12: 2009 | C12: 0.7576
B13: 2010 | C13: 0.1795
B14: 2011 | C14: -0.2462
B15: 2012 | C15: 0.277
B16: 2013 | C16: 0.0676
B17: 2014 | C17: 0.3139
... B29: 2026 | C29: 0.1051

Sheet Instrinsic Growth
B2: Calculation Of ROIC | G2: =HISTORIACLFINANCIALS!$H$3 -> 44286 | H2: =HISTORIACLFINANCIALS!I3 -> 44651 | I2: =HISTORIACLFINANCIALS!J3 -> 45016 | J2: =HISTORIACLFINANCIALS!K3 -> 45382 | K2: =HISTORIACLFINANCIALS!L3 -> 45747
B4: Current Asset
B5: ='RAW-FS'!B36 -> Inventories | G5: ='RAW-FS'!J36 -> 3049 | H5: ='RAW-FS'!K36 -> 3532 | I5: ='RAW-FS'!L36 -> 4284 | J5: ='RAW-FS'!M36 -> 5318 | K5: ='RAW-FS'!N36 -> 6913
B6: ='RAW-FS'!B37 -> Trade receivables | G6: ='RAW-FS'!J37 -> 1280 | H6: ='RAW-FS'!K37 -> 2034 | I6: ='RAW-FS'!L37 -> 3301 | J6: ='RAW-FS'!M37 -> 4597 | K6: ='RAW-FS'!N37 -> 6540
B7: ='RAW-FS'!B39 -> Loans n Advances | G7: ='RAW-FS'!J39 -> 1412 | H7: ='RAW-FS'!K39 -> 2880 | I7: ='RAW-FS'!L39 -> 2828 | J7: ='RAW-FS'!M39 -> 266 | K7: ='RAW-FS'!N39 -> 851
B8: ='RAW-FS'!B40 -> Other asset items | G8: ='RAW-FS'!J40 -> 3158 | H8: ='RAW-FS'!K40 -> 4448 | I8: ='RAW-FS'!L40 -> 4223 | J8: ='RAW-FS'!M40 -> 9400 | K8: ='RAW-FS'!N40 -> 9937
B9: Total Current Asset | G9: =SUM(G5:G8) -> 8899 | H9: =SUM(H5:H8) -> 12894 | I9: =SUM(I5:I8) -> 14636 | J9: =SUM(J5:J8) -> 19581 | K9: =SUM(K5:K8) -> 24241
B11: Current Liablities
B12: ='RAW-FS'!B14 -> Trade Payables | G12: ='RAW-FS'!C14 -> 4999 | H12: ='RAW-FS'!D14 -> 5514 | I12: ='RAW-FS'!E14 -> 7409 | J12: ='RAW-FS'!F14 -> 8369 | K12: ='RAW-FS'!G14 -> 10499
B13: ='RAW-FS'!B15 -> Advance from Customers | G13: ='RAW-FS'!C15 -> 209 | H13: ='RAW-FS'!D15 -> 428 | I13: ='RAW-FS'!E15 -> 506 | J13: ='RAW-FS'!F15 -> 941 | K13: ='RAW-FS'!G15 -> 1152
B14: ='RAW-FS'!B16 -> Other liability items | G14: ='RAW-FS'!C16 -> 2755 | H14: ='RAW-FS'!D16 -> 3538 | I14: ='RAW-FS'!E16 -> 3950 | J14: ='RAW-FS'!F16 -> 5076 | K14: ='RAW-FS'!G16 -> 5900
B15: Total Currrent Liablity | G15: =SUM(G12:G14) -> 7963 | H15: =SUM(H12:H14) -> 9480 | I15: =SUM(I12:I14) -> 11865 | J15: =SUM(J12:J14) -> 14386 | K15: =SUM(K12:K14) -> 17551
A17: # | B17: Net Working Capital | G17: =G9-G15 -> 936 | H17: =H9-H15 -> 3414 | I17: =I9-I15 -> 2771 | J17: =J9-J15 -> 5195 | K17: =K9-K15 -> 6690
B19: Fixed Assets
B20: ='RAW-FS'!B20 -> Land | G20: ='RAW-FS'!J20 -> 4566 | H20: ='RAW-FS'!K20 -> 4592 | I20: ='RAW-FS'!L20 -> 6757 | J20: ='RAW-FS'!M20 -> 6896 | K20: ='RAW-FS'!N20 -> 6921
B21: ='RAW-FS'!B21 -> Building | G21: ='RAW-FS'!J21 -> 2831 | H21: ='RAW-FS'!K21 -> 2955 | I21: ='RAW-FS'!L21 -> 3206 | J21: ='RAW-FS'!M21 -> 5604 | K21: ='RAW-FS'!N21 -> 8158
B22: ='RAW-FS'!B22 -> Plant Machinery | G22: ='RAW-FS'!J22 -> 22262 | H22: ='RAW-FS'!K22 -> 22712 | I22: ='RAW-FS'!L22 -> 26174 | J22: ='RAW-FS'!M22 -> 44745 | K22: ='RAW-FS'!N22 -> 51915
B23: ='RAW-FS'!B23 -> Computers | G23: ='RAW-FS'!J23 -> 292 | H23: ='RAW-FS'!K23 -> 324 | I23: ='RAW-FS'!L23 -> 368 | J23: ='RAW-FS'!M23 -> 601 | K23: ='RAW-FS'!N23 -> 698
B24: ='RAW-FS'!B24 -> Furniture n fittings | G24: ='RAW-FS'!J24 -> 403 | H24: ='RAW-FS'!K24 -> 445 | I24: ='RAW-FS'!L24 -> 485 | J24: ='RAW-FS'!M24 -> 636 | K24: ='RAW-FS'!N24 -> 698
B25: ='RAW-FS'!B25 -> Railway sidings | G25: ='RAW-FS'!J25 -> 0 | H25: ='RAW-FS'!K25 -> 0 | I25: ='RAW-FS'!L25 -> 73 | J25: ='RAW-FS'!M25 -> 74 | K25: ='RAW-FS'!N25 -> 94
B26: ='RAW-FS'!B26 -> Vehicles | G26: ='RAW-FS'!J26 -> 174 | H26: ='RAW-FS'!K26 -> 248 | I26: ='RAW-FS'!L26 -> 282 | J26: ='RAW-FS'!M26 -> 448 | K26: ='RAW-FS'!N26 -> 568
B27: ='RAW-FS'!B27 -> Intangible Assets | G27: ='RAW-FS'!J27 -> 0 | H27: ='RAW-FS'!K27 -> 0 | I27: ='RAW-FS'!L27 -> 0 | J27: ='RAW-FS'!M27 -> 0 | K27: ='RAW-FS'!N27 -> 0
B28: ='RAW-FS'!B28 -> Other fixed assets | G28: ='RAW-FS'!J28 -> 967 | H28: ='RAW-FS'!K28 -> 1254 | I28: ='RAW-FS'!L28 -> 1660 | J28: ='RAW-FS'!M28 -> 1783 | K28: ='RAW-FS'!N28 -> 2002
B29: Gross Block | G29: =SUM(G20:G28) -> 31495 | H29: =SUM(H20:H28) -> 32530 | I29: =SUM(I20:I28) -> 39005 | J29: =SUM(J20:J28) -> 60787 | K29: =SUM(K20:K28) -> 71054
B30: Accumlated Depreciation | G30: ='RAW-FS'!J31 -> 16508 | H30: ='RAW-FS'!K31 -> 18783 | I30: ='RAW-FS'!L31 -> 21174 | J30: ='RAW-FS'!M31 -> 32922 | K30: ='RAW-FS'!N31 -> 38070
A31: # | B31: Net Fixed Assets | G31: =SUM(G29:G30) -> 48003 | H31: =SUM(H29:H30) -> 51313 | I31: =SUM(I29:I30) -> 60179 | J31: =SUM(J29:J30) -> 93709 | K31: =SUM(K29:K30) -> 109124
B33: Invested Capital | G33: =SUM(G31,G17) -> 48939 | H33: =SUM(H31,H17) -> 54727 | I33: =SUM(I31,I17) -> 62950 | J33: =SUM(J31,J17) -> 98904 | K33: =SUM(K31,K17) -> 115814
B34: EBIT | G34: =HISTORIACLFINANCIALS!H26+HISTORIACLFINANCIALS!H20 -> 2723.4 | H34: =HISTORIACLFINANCIALS!I26+HISTORIACLFINANCIALS!I20 -> 3052.9 | I34: =HISTORIACLFINANCIALS!J26+HISTORIACLFINANCIALS!J20 -> 5960.4 | J34: =HISTORIACLFINANCIALS!K26+HISTORIACLFINANCIALS!K20 -> 13211.7 | K34: =HISTORIACLFINANCIALS!L26+HISTORIACLFINANCIALS!L20 -> 20417.8
B36: ROIC | G36: =G34/G33 -> 0.055648869 | H36: =H34/H33 -> 0.055784165 | I36: =I34/I33 -> 0.09468467 | J36: =J34/J33 -> 0.13358105 | K36: =K34/K33 -> 0.1762982
B39: Calculation of Reinvestment Rate | G39: =G2 -> 44286 | H39: =H2 -> 44651 | I39: =I2 -> 45016 | J39: =J2 -> 45382 | K39: =K2 -> 45747
B41: Net Capex | G41: =-SUM(DATA!J13:J14) -> 2328 | H41: =-SUM(DATA!K13:K14) -> 3323 | I41: =-SUM(DATA!L13:L14) -> 6247 | J41: =-SUM(DATA!M13:M14) -> 9155 | K41: =-SUM(DATA!N13:N14) -> 10603
B42: Change In Working Capital | G42: - | H42: =H17-G17 -> 2478 | I42: =I17-H17 -> -643 | J42: =J17-I17 -> 2424 | K42: =K17-J17 -> 1495
B44: EBIT | G44: =G34 -> 2723.4 | H44: =H34 -> 3052.9 | I44: =I34 -> 5960.4 | J44: =J34 -> 13211.7 | K44: =K34 -> 20417.8
B45: Marginal Tax Rate | G45: 0.25 | H45: 0.25 | I45: 0.25 | J45: 0.25 | K45: 0.25
B46: EBIT(1-T) | G46: =G44*(1-G45) -> 2042.55 | H46: =H44*(1-H45) -> 2289.675 | I46: =I44*(1-I45) -> 4470.3 | J46: =J44*(1-J45) -> 9908.775 | K46: =K44*(1-K45) -> 15313.35
B48: Reinvestment | G48: - | H48: =SUM(H41:H42) -> 5801 | I48: =SUM(I41:I42) -> 5604 | J48: =SUM(J41:J42) -> 11579 | K48: =SUM(K41:K42) -> 12098
B50: Reinvestment Rate | G50: - | H50: =H48/H46 -> 2.5335473 | I50: =I48/I46 -> 1.2536071 | J50: =J48/J46 -> 1.1685602 | K50: =K48/K46 -> 0.79002961
J52: 4 year Average | K52: =AVERAGE(H50:K50) -> 1.4364361
J53: 4 Year Median | K53: =MEDIAN(H50:K50) -> 1.2110837
B55: Calculation Of Growth Rate | G55: =G2 -> 44286 | H55: =H2 -> 44651 | I55: =I2 -> 45016 | J55: =J2 -> 45382 | K55: =K2 -> 45747
B57: =B50 -> Reinvestment Rate | G57: - | H57: =H50 -> 2.5335473 | I57: =I50 -> 1.2536071 | J57: =J50 -> 1.1685602 | K57: =K50 -> 0.79002961
B58: ROIC | G58: =G36 -> 0.055648869 | H58: =H36 -> 0.055784165 | I58: =I36 -> 0.09468467 | J58: =J36 -> 0.13358105 | K58: =K36 -> 0.1762982
B60: Instrinsic Growth | G60: - | H60: =H57*H58 -> 0.14133182 | I60: =I57*I58 -> 0.11869738 | J60: =J57*J58 -> 0.1560975 | K60: =K57*K58 -> 0.1392808
J62: 4 year Average | K62: =AVERAGE(H60:K60) -> 0.13885187
J63: 4 Year Median | K63: =MEDIAN(H60:K60) -> 0.14030631

Sheet DCF
B3: Calculation Of Present Value of FCFF | F3: ='Instrinsic Growth'!$K$2 -> 45747 | G3: =F3+365 -> 46112 | H3: =G3+365 -> 46477 | I3: =H3+365 -> 46842 | J3: =I3+365 -> 47207 | K3: =J3+365 -> 47572
B5: EBIT | F5: ='Instrinsic Growth'!K34 -> 20417.8 | G5: =F5*(1+$C$17) -> 23282.546 | H5: =G5*(1+$C$17) -> 26549.234 | I5: =H5*(1+$C$17) -> 30274.26 | J5: =I5*(1+$C$17) -> 34521.929 | K5: =J5*(1+$C$17) -> 39365.574
B6: Tax Rate | F6: 0.25 | G6: 0.25 | H6: 0.25 | I6: 0.25 | J6: 0.25 | K6: 0.25
B7: EBIT(1-T) | F7: =F5*(1-F6) -> 15313.35 | G7: =G5*(1-G6) -> 17461.91 | H7: =H5*(1-H6) -> 19911.926 | I7: =I5*(1-I6) -> 22705.695 | J7: =J5*(1-J6) -> 25891.447 | K7: =K5*(1-K6) -> 29524.18
B8: Less: Reinvestment Rate | F8: 0.36 | G8: 0.36 | H8: 0.36 | I8: 0.36 | J8: 0.36 | K8: 0.36
B10: Free Cash Flow to firm(FCFF) | F10: =F7*(1-F8) -> 9800.544 | G10: =G7*(1-G8) -> 11175.622 | H10: =H7*(1-H8) -> 12743.633 | I10: =I7*(1-I8) -> 14531.645 | J10: =J7*(1-J8) -> 16570.526 | K10: =K7*(1-K8) -> 18895.475
B11: Mid Year Convention | G11: 0.5 | H11: =G11+1 -> 1.5 | I11: =H11+1 -> 2.5 | J11: =I11+1 -> 3.5 | K11: =J11+1 -> 4.5
B12: Discounting Factor | G12: =1/(1+$C$19)^G11 -> 0.93271706 | H12: =1/(1+$C$19)^H11 -> 0.81142758 | I12: =1/(1+$C$19)^I11 -> 0.70591044 | J12: =1/(1+$C$19)^J11 -> 0.61411464 | K12: =1/(1+$C$19)^K11 -> 0.53425586
B14: PV of FCFF | G14: =G10*G12 -> 10423.693 | H14: =H10*H12 -> 10340.535 | I14: =I10*I12 -> 10258.04 | J14: =J10*J12 -> 10176.203 | K14: =K10*K12 -> 10095.018
B17: Expected Growth | C17: ='Instrinsic Growth'!K63 -> 0.14030631
B18: Terminal Growth | C18: 0.0538 | D18: # Taken from RBI website
B19: WACC | C19: =WACC!J45 -> 0.14947666
B21: Calculation Of Terminal Value
B23: FCFF(N+1) | C23: =K10*(1+C17) -> 21546.63
B24: WACC | C24: =C19 -> 0.14947666
B25: Terminal Growth Rate | C25: =C18 -> 0.0538
B27: Terminal Value | C27: =C23/(C24-C25) -> 225202.57
B29: Calculation Of Equity Value Per share
B31: PV of FCFF | C31: =SUM(G14:K14) -> 51293.489
B32: PV of Terminal Value | C32: =C27*K12 -> 120315.79
B33: Value of Operating Asset | C33: =SUM(C31:C32) -> 171609.28
B35: Add: Cash | C35: ='Data Sheet'!K69 -> 552.9
B36: Less: Debt | C36: =HISTORIACLFINANCIALS!L48 -> 87
B37: Value of Equity | C37: =C33+C35-C36 -> 172075.18
B38: No of Shares | C38: ='Data Sheet'!B6 -> 31.440256
B39: Equity Value Per Share | C39: =C37/C38 -> 5473.0846
B41: Share Price | C41: 15067
B42: Discount/Premium | C42: =C41/C39-1 -> 1.7529266

Sheet Data_Room>

Sheet Data Sheet
A1: COMPANY NAME | B1: MARUTI SUZUKI INDIA LTD | E1: =IF(B2<>B3, "A NEW VERSION OF THE WORKSHEET IS AVAILABLE", "")
A2: LATEST VERSION | B2: 2.1 | E2: PLEASE DO NOT MAKE ANY CHANGES TO THIS SHEET
A3: CURRENT VERSION | B3: 2.1
A5: META
A6: Number of shares | B6: =IF(B9>0, B9/B8, 0) -> 31.440256
A7: Face Value | B7: 5
A8: Current Price | B8: 14294.95
A9: Market Capitalization | B9: 449436.89
A15: PROFIT & LOSS
A16: Report Date | B16: 42460 | C16: 42825 | D16: 43190 | E16: 43555 | F16: 43921 | G16: 44286 | H16: 44651 | I16: 45016 | J16: 45382 | K16: 45747
A17: Sales | B17: 57589 | C17: 68085 | D17: 79809.4 | E17: 86068.5 | F17: 75660 | G17: 70372 | H17: 88329.8 | I17: 117571.3 | J17: 141858.2 | K17: 152913
A18: Raw Material Cost | B18: 38701.2 | C18: 47121.5 | D18: 54945.3 | E18: 59346.6 | F18: 53402 | G18: 50550.5 | H18: 66137.1 | I18: 86654.7 | J18: 100119.5 | K18: 108718.3
A19: Change in Inventory | B19: -4.8 | C19: 379.3 | D19: -40.8 | E19: -211.6 | F19: 238.7 | G19: -273.6 | H19: 93.1 | I19: 403.9 | J19: 378.6 | K19: 1227.5
A20: Power and Fuel | B20: 694.1 | C20: 518.6 | D20: 673.4 | E20: 863.3 | F20: 699.5 | G20: 476.6 | H20: 630.9 | I20: 790 | J20: 1033.4 | K20: 1052.6
A21: Other Mfr. Exp | B21: 427.8 | C21: 382.9 | D21: 462.1 | E21: 475.7 | F21: 378.1 | G21: 683.3 | H21: 852.5 | I21: 1120.7 | J21: 939.3 | K21: 1994.4
A22: Employee Cost | B22: 2000.3 | C22: 2360.3 | D22: 2863.4 | E22: 3285 | F22: 3416.2 | G22: 3431.6 | H22: 4051.4 | I22: 4634.6 | J22: 6301.6 | K22: 7026
A23: Selling and admin | B23: 5367.3 | C23: 6111.3 | D23: 6755.3 | E23: 8390.3 | F23: 8456.3 | G23: 7924 | H23: 9119.1 | I23: 11695 | J23: 12082.6 | K23: 11523.3
A24: Other Expenses | B24: 1369.4 | C24: 1548.4 | D24: 1951.2 | E24: 2439.7 | F24: 2191.6 | G24: 1621.8 | H24: 1879.9 | I24: 2051 | J24: 3134.1 | K24: 3602.3
A25: Other Income | B25: 1464.1 | C25: 2399.2 | D25: 2154.6 | E25: 2664.2 | F25: 3410.4 | G25: 3046.3 | H25: 1860.8 | I25: 2306.6 | J25: 4247.6 | K25: 5198.8
A26: Depreciation | B26: 2821.8 | C26: 2603.9 | D26: 2759.8 | E26: 3020.8 | F26: 3528.4 | G26: 3034.1 | H26: 2789 | I26: 2825.7 | J26: 5255.8 | K26: 5608.2
A27: Interest | B27: 81.7 | C27: 89.4 | D27: 345.8 | E27: 75.9 | F27: 134.2 | G27: 101.8 | H27: 126.6 | I27: 187 | J27: 193.6 | K27: 194.2
... A31: Dividend Amount | B31: 1057 | C31: 2265 | D31: 2416 | E31: 2416 | F31: 1812 | G31: 1359 | H31: 1812 | I31: 2718 | J31: 3930 | K31: 4244.4
A40: Quarters
A41: Report Date | B41: 45199 | C41: 45291 | D41: 45382 | E41: 45473 | F41: 45565 | G41: 45657 | H41: 45747 | I41: 45838 | J41: 45930 | K41: 46022
A42: Sales | B42: 37339.4 | C42: 33512.8 | D42: 38471.2 | E42: 35779.4 | F42: 37449.2 | G42: 38764.3 | H42: 40920.1 | I42: 38605.2 | J42: 42344.2 | K42: 49904.1
A43: Expenses | B43: 32027.9 | C43: 29072.8 | D43: 33250.1 | E43: 30672.8 | F43: 32450.4 | G43: 33687.8 | H43: 36076.1 | I43: 33982.6 | J43: 37258.2 | K43: 44331
A44: Other Income | B44: 957.8 | C44: 1052.9 | D44: 1261 | E44: 1118.1 | F44: 1570.5 | G44: 1124.8 | H44: 1583.1 | I44: 1923.7 | J44: 1013.5 | K44: 1140.5
A45: Depreciation | B45: 1341.9 | C45: 1301.5 | D45: 1298.3 | E45: 1331.7 | F45: 1385.7 | G45: 1429 | H45: 1461.8 | I45: 1556 | J45: 1703 | K45: 1734.6
A46: Interest | B46: 35.1 | C46: 35.8 | D46: 76.2 | E46: 57.3 | F46: 43 | G46: 46.3 | H46: 47.6 | I46: 46.8 | J46: 57.2 | K46: 61.7
A47: Profit before tax | B47: 4892.3 | C47: 4155.6 | D47: 5107.6 | E47: 4835.7 | F47: 5140.6 | G47: 4726 | H47: 4917.7 | I47: 4943.5 | J47: 4339.3 | K47: 4917.3
A48: Tax | B48: 1106.1 | C48: 948.8 | E48: 1076 | F48: 2038.1 | G48: 999.1 | H48: 1006.6 | I48: 1151.1 | J48: 990.3 | K48: 1038.2
A49: Net profit | B49: 3786.2 | C49: 3206.8 | D49: 3952.3 | E49: 3759.7 | F49: 3102.5 | G49: 3726.9 | H49: 3911.1 | I49: 3792.4 | J49: 3349 | K49: 3879.1
A50: Operating Profit | B50: 5311.5 | C50: 4440 | D50: 5221.1 | E50: 5106.6 | F50: 4998.8 | G50: 5076.5 | H50: 4844 | I50: 4622.6 | J50: 5086 | K50: 5573.1
A55: BALANCE SHEET
A56: Report Date | B56: 42460 | C56: 42825 | D56: 43190 | E56: 43555 | F56: 43921 | G56: 44286 | H56: 44651 | I56: 45016 | J56: 45382 | K56: 45747
A57: Equity Share Capital | B57: 151 | C57: 151 | D57: 151 | E57: 151 | F57: 151 | G57: 151 | H57: 151 | I57: 151 | J57: 157.2 | K57: 157.2
A58: Reserves | B58: 30465 | C58: 36924.1 | D58: 42408.4 | E58: 46941.1 | F58: 49262 | G58: 52349.6 | H58: 55182.5 | I58: 61640.3 | J58: 85478.8 | K58: 96082.7
A59: Borrowings | B59: 230.9 | C59: 483.6 | D59: 120.8 | E59: 159.6 | F59: 184.1 | G59: 540.9 | H59: 425.5 | I59: 1247.3 | J59: 118.6 | K59: 87
A60: Other Liabilities | B60: 11878.6 | C60: 14401.8 | D60: 17568.2 | E60: 16717 | F60: 14030.6 | G60: 18334.6 | H60: 18896.5 | I60: 21558.3 | J60: 29549.5 | K60: 35644.3
A61: Total | B61: 42725.5 | C61: 51960.5 | D61: 60248.4 | E61: 63968.7 | F61: 63627.7 | G61: 71376.1 | H61: 74655.5 | I61: 84596.9 | J61: 115304.1 | K61: 131971.2
A62: Net Block | B62: 12529.6 | C62: 13310.7 | D62: 13388.8 | E62: 15437.3 | F62: 15744.4 | G62: 14988.7 | H62: 13747.2 | I62: 17830.4 | J62: 27864.8 | K62: 32982.7
A63: Capital Work in Progress | B63: 1006.9 | C63: 1252.3 | D63: 2132.1 | E63: 1606.9 | F63: 1415.2 | G63: 1496.8 | H63: 2936.5 | I63: 2904.1 | J63: 7734.8 | K63: 7929
A64: Investments | B64: 20675.8 | C64: 29150.6 | D64: 36123.1 | E64: 37503.6 | F64: 37488 | G64: 42944.8 | H64: 42034.7 | I64: 49184.3 | J64: 57296 | K64: 66265.4
A65: Other Assets | B65: 8513.2 | C65: 8246.9 | D65: 8604.4 | E65: 9420.9 | F65: 8980.1 | G65: 11945.8 | H65: 15937.1 | I65: 14678.1 | J65: 22408.5 | K65: 24794.1
A66: Total | B66: 42725.5 | C66: 51960.5 | D66: 60248.4 | E66: 63968.7 | F66: 63627.7 | G66: 71376.1 | H66: 74655.5 | I66: 84596.9 | J66: 115304.1 | K66: 131971.2
A67: Receivables | B67: 1323.4 | C67: 1202.6 | D67: 1465.4 | E67: 2312.8 | F67: 1977.7 | G67: 1279.9 | H67: 2034.5 | I67: 3301.4 | J67: 4596.8 | K67: 6539.7
... A70: No. of Equity Shares | B70: 302080060 | C70: 302080060 | D70: 302080060 | E70: 302080060 | F70: 302080060 | G70: 302080060 | H70: 302080060 | I70: 302080060 | J70: 314402574 | K70: 314402574
A71: New Bonus Shares
A72: Face value | B72: 5 | C72: 5 | D72: 5 | E72: 5 | F72: 5 | G72: 5 | H72: 5 | I72: 5 | J72: 5 | K72: 5
A80: CASH FLOW:
A81: Report Date | B81: 42460 | C81: 42825 | D81: 43190 | E81: 43555 | F81: 43921 | G81: 44286 | H81: 44651 | I81: 45016 | J81: 45382 | K81: 45747
A82: Cash from Operating Activity | B82: 8482.5 | C82: 10282 | D82: 11787.9 | E82: 6600.9 | F82: 3495.8 | G82: 8856.2 | H82: 1840.5 | I82: 9251.4 | J82: 16801.1 | K82: 16136.2
A83: Cash from Investing Activity | B83: -7230.4 | C83: -9173.2 | D83: -8301.7 | E83: -3539.9 | F83: -556.6 | G83: -7291.3 | H83: -239.2 | I83: -8036.1 | J83: -11864.8 | K83: -14456.1
A84: Cash from Financing Activity | B84: -1236.6 | C84: -1129.3 | D84: -3436.1 | E84: -2947.9 | F84: -3104.3 | G84: -1544.9 | H84: -1607 | I84: -1213.1 | J84: -4062 | K84: -4155.1
A85: Net Cash Flow | B85: 15.5 | C85: -20.5 | D85: 50.1 | E85: 113.1 | F85: -165.1 | G85: 20 | H85: -5.7 | I85: 2.2 | J85: 874.3 | K85: -2475
A90: PRICE: | B90: 3716.3 | C90: 6015.7 | D90: 8861.1 | E90: 6672.55 | F90: 4288.3 | G90: 6859.2 | H90: 7561.3 | I90: 8292.15 | J90: 12600.35 | K90: 11522.15
A92: DERIVED:
A93: Adjusted Equity Shares in Cr | B93: 30.21 | C93: 30.21 | D93: 30.21 | E93: 30.21 | F93: 30.21 | G93: 30.21 | H93: 30.21 | I93: 30.21 | J93: 31.44 | K93: 31.44

Sheet DATA
C2: 41699 | D2: 42064 | E2: 42430 | F2: 42795 | G2: 43160 | H2: 43525 | I2: 43891 | J2: 44256 | K2: 44621 | L2: 44986 | M2: 45352 | N2: 45717
B3: Cash from Operating Activity - | C3: 4995 | D3: 6449 | E3: 8482 | F3: 10282 | G3: 11788 | H3: 6601 | I3: 3496 | J3: 8856 | K3: 1840 | L3: 9251 | M3: 16801 | N3: 16136
B4: Profit from operations | C4: 5111 | D4: 6779 | E4: 8935 | F4: 10413 | G4: 12036 | H4: 11060 | I4: 7503 | J4: 5531 | K4: 5832 | L4: 11112 | M4: 18676 | N4: 20322
B5: Receivables | C5: 46 | D5: 345 | E5: -204 | F5: 122 | G5: -262 | H5: -851 | I5: 340 | J5: 696 | K5: -764 | L5: -1258 | M5: -1316 | N5: -1969
B6: Inventory | C6: 124 | D6: -982 | E6: -450 | F6: -131 | G6: 104 | H6: -162 | I6: 109 | J6: 165 | K6: -483 | L6: -751 | M6: 125 | N6: -1595
B7: Payables | C7: 813 | D7: 712 | E7: 1789 | F7: 979 | G7: 2128 | H7: -858 | I7: -2155 | J7: 2680 | K7: -396 | L7: 2008 | M7: 3321 | N7: 3509
B8: Loans Advances | C8: -563 | D8: 23 | E8: -1 | F8: 1 | G8: 0 | H8: -13 | I8: -1 | J8: -6 | K8: -8 | L8: 1 | M8: -3 | N8: -10
B9: Other WC items | C9: 321 | D9: 648 | E9: 325 | F9: 1222 | G9: 839 | H9: 569 | I9: -863 | J9: 801 | K9: -1162 | L9: 374 | M9: -406 | N9: -313
B10: Working capital changes | C10: 742 | D10: 745 | E10: 1460 | F10: 2192 | G10: 2808 | H10: -1315 | I10: -2570 | J10: 4336 | K10: -2813 | L10: 373 | M10: 1722 | N10: -378
B11: Direct taxes | C11: -858 | D11: -1075 | E11: -1912 | F11: -2323 | G11: -3056 | H11: -3144 | I11: -1438 | J11: -1011 | K11: -1178 | L11: -2233 | M11: -3597 | N11: -3807
B12: Cash from Investing Activity - | C12: -4997 | D12: -4491 | E12: -7230 | F12: -9173 | G12: -8302 | H12: -3540 | I12: -557 | J12: -7291 | K12: -239 | L12: -8036 | M12: -11865 | N12: -14456
B13: Fixed assets purchased | C13: -3545 | D13: -3058 | E13: -2469 | F13: -3391 | G13: -3912 | H13: -4872 | I13: -3437 | J13: -2370 | K13: -3459 | L13: -6347 | M13: -9200 | N13: -10641
B14: Fixed assets sold | C14: 9 | D14: 16 | E14: 12 | F14: 16 | G14: 26 | H14: 170 | I14: 37 | J14: 42 | K14: 136 | L14: 100 | M14: 45 | N14: 38
... B29: Net Cash Flow | C29: -76 | D29: -45 | E29: 16 | F29: -20 | G29: 50 | H29: 113 | I29: -165 | J29: 20 | K29: -6 | L29: 2 | M29: 874 | N29: -2475

Sheet RAW-FS
B2: Particulars | C2: 41699 | D2: 42064 | E2: 42430 | F2: 42795 | G2: 43160 | H2: 43525 | I2: 43891 | J2: 44256 | K2: 44621 | L2: 44986 | M2: 45352 | N2: 45717 | O2: 45901
B4: Equity Capital | C4: 151 | D4: 151 | E4: 151 | F4: 151 | G4: 151 | H4: 151 | I4: 151 | J4: 151 | K4: 151 | L4: 151 | M4: 157 | N4: 157 | O4: 157
B5: Reserves | C5: 21345 | D5: 24167 | E5: 30465 | F5: 36924 | G5: 42408 | H5: 46941 | I5: 49262 | J5: 52350 | K5: 55182 | L5: 61640 | M5: 85479 | N5: 96083 | O5: 99587
B6: Borrowings -
B7: Long term Borrowings | C7: 627 | D7: 278 | E7: 0 | F7: 0 | G7: 10 | H7: 8 | I7: 5 | J7: 3 | K7: 0 | L7: 0 | M7: 0 | N7: 0 | O7: 0
B8: Short term Borrowings | C8: 1238 | D8: 52 | E8: 77 | F8: 484 | G8: 111 | H8: 150 | I8: 106 | J8: 489 | K8: 382 | L8: 1216 | M8: 33 | N8: 0 | O8: 0
B9: Lease Liabilities | C9: 0 | D9: 0 | E9: 0 | F9: 0 | G9: 0 | H9: 0 | I9: 70 | J9: 47 | K9: 41 | L9: 32 | M9: 86 | N9: 87 | O9: 100
B10: Other Borrowings | C10: 139 | D10: 335 | E10: 154 | F10: 0 | G10: 0 | H10: 2 | I10: 2 | J10: 3 | K10: 3 | L10: 0 | M10: 0 | N10: 0
B12: Other Liabilities -
B13: Non controlling int | C13: 12 | D13: 13 | E13: 14 | F13: 15 | G13: 16 | H13: 18 | I13: 19 | J13: 0 | K13: 0 | L13: 0 | M13: 0 | N13: 0 | O13: 0
B14: Trade Payables | C14: 4999 | D14: 5514 | E14: 7409 | F14: 8369 | G14: 10499 | H14: 9638 | I14: 7499 | J14: 10168 | K14: 9765 | L14: 11786 | M14: 16988 | N14: 20502 | O14: 22282
B15: Advance from Customers | C15: 209 | D15: 428 | E15: 506 | F15: 941 | G15: 1152 | H15: 418 | I15: 468 | J15: 1019 | K15: 1124 | L15: 1456 | M15: 1464 | N15: 1135
B16: Other liability items | C16: 2755 | D16: 3538 | E16: 3950 | F16: 5076 | G16: 5900 | H16: 6644 | I16: 6045 | J16: 7148 | K16: 8007 | L16: 8317 | M16: 11098 | N16: 14008 | O16: 16328
B17: Total Liabilities | C17: 31476 | D17: 34477 | E17: 42726 | F17: 51960 | G17: 60248 | H17: 63969 | I17: 63628 | J17: 71376 | K17: 74656 | L17: 84597 | M17: 115304 | N17: 131971 | O17: 138453
B19: Fixed Assets -
B20: Land | C20: 1630 | D20: 2100 | E20: 1902 | F20: 1963 | G20: 3212 | H20: 3914 | I20: 4569 | J20: 4566 | K20: 4592 | L20: 6757 | M20: 6896 | N20: 6921
B21: Building | C21: 1760 | D21: 1882 | E21: 1513 | F21: 1835 | G21: 1983 | H21: 2333 | I21: 2697 | J21: 2831 | K21: 2955 | L21: 3206 | M21: 5604 | N21: 8158
B22: Plant Machinery | C22: 18866 | D22: 21802 | E22: 11163 | F22: 13888 | G22: 15082 | H22: 18550 | I22: 20775 | J22: 22262 | K22: 22712 | L22: 26174 | M22: 44745 | N22: 51915
B23: Computers | C23: 172 | D23: 193 | E23: 83 | F23: 135 | G23: 172 | H23: 208 | I23: 238 | J23: 292 | K23: 324 | L23: 368 | M23: 601 | N23: 698
B24: Furniture n fittings | C24: 133 | D24: 144 | E24: 109 | F24: 140 | G24: 206 | H24: 270 | I24: 347 | J24: 403 | K24: 445 | L24: 485 | M24: 636 | N24: 698
B25: Railway sidings | C25: 0 | D25: 0 | E25: 0 | F25: 0 | G25: 0 | H25: 0 | I25: 0 | J25: 0 | K25: 0 | L25: 73 | M25: 74 | N25: 94
B26: Vehicles | C26: 92 | D26: 108 | E26: 104 | F26: 130 | G26: 162 | H26: 184 | I26: 206 | J26: 174 | K26: 248 | L26: 282 | M26: 448 | N26: 568
B27: Intangible Assets | C27: 0 | D27: 0 | E27: 0 | F27: 0 | G27: 0 | H27: 0 | I27: 0 | J27: 0 | K27: 0 | L27: 0 | M27: 0 | N27: 0 | O27: 896
B28: Other fixed assets | C28: 452 | D28: 674 | E28: 468 | F28: 589 | G28: 640 | H28: 907 | I28: 937 | J28: 967 | K28: 1254 | L28: 1660 | M28: 1783 | N28: 2002
B30: Gross Block | C30: 23105 | D30: 26902 | E30: 15343 | F30: 18680 | G30: 21458 | H30: 26365 | I30: 29768 | J30: 31496 | K30: 32530 | L30: 39004 | M30: 60787 | N30: 71052
B31: Accumulated Depreciation | C31: 12071 | D31: 14412 | E31: 2813 | F31: 5370 | G31: 8069 | H31: 10928 | I31: 14024 | J31: 16508 | K31: 18783 | L31: 21174 | M31: 32922 | N31: 38070
B32: CWIP | C32: 2640 | D32: 1890 | E32: 1007 | F32: 1252 | G32: 2132 | H32: 1607 | I32: 1415 | J32: 1497 | K32: 2936 | L32: 2904 | M32: 7735 | N32: 7929 | O32: 7902
B33: Investments | C33: 10527 | D33: 13298 | E33: 20676 | F33: 29151 | G33: 36123 | H33: 37504 | I33: 37488 | J33: 42945 | K33: 42035 | L33: 49184 | M33: 57296 | N33: 66265 | O33: 65473
B35: Other Assets -
B36: Inventories | C36: 1763 | D36: 2745 | E36: 3133 | F36: 3264 | G36: 3160 | H36: 3323 | I36: 3214 | J36: 3049 | K36: 3532 | L36: 4284 | M36: 5318 | N36: 6913 | O36: 10850
B37: Trade receivables | C37: 1489 | D37: 1144 | E37: 1323 | F37: 1203 | G37: 1465 | H37: 2313 | I37: 1978 | J37: 1280 | K37: 2034 | L37: 3301 | M37: 4597 | N37: 6540 | O37: 7330
B38: Cash Equivalents | C38: 649 | D38: 43 | E38: 51 | F38: 24 | G38: 74 | H38: 188 | I38: 29 | J38: 3047 | K38: 3042 | L38: 42 | M38: 2827 | N38: 553 | O38: 668
B39: Loans n Advances | C39: 188 | D39: 126 | E39: 623 | F39: 688 | G39: 1290 | H39: 1160 | I39: 1362 | J39: 1412 | K39: 2880 | L39: 2828 | M39: 266 | N39: 851 | O39: 519
B40: Other asset items | C40: 3187 | D40: 2741 | E40: 3384 | F40: 3069 | G40: 2615 | H40: 2438 | I40: 2398 | J40: 3158 | K40: 4448 | L40: 4223 | M40: 9400 | N40: 9937 | O40: 10210
B41: Total Assets | C41: 31476 | D41: 34477 | E41: 42726 | F41: 51960 | G41: 60248 | H41: 63969 | I41: 63628 | J41: 71376 | K41: 74656 | L41: 84597 | M41: 115304 | N41: 131971 | O41: 138453
